[{"timing_sec":2.463,"notes_attribute":1,"notes_level":1,"effect":3,"effect_value":0.316,"position":6},{"timing_sec":2.779,"notes_attribute":1,"notes_level":1,"effect":3,"effect_value":0.316,"position":3},{"timing_sec":3.095,"notes_attribute":1,"notes_level":1,"effect":3,"effect_value":0.316,"position":7},{"timing_sec":3.411,"notes_attribute":1,"notes_level":1,"effect":3,"effect_value":1.263,"position":4},{"timing_sec":4.042,"notes_attribute":1,"notes_level":1,"effect":2,"effect_value":0.079,"position":6},{"timing_sec":4.674,"notes_attribute":1,"notes_level":1,"effect":3,"effect_value":2.526,"position":7},{"timing_sec":5.305,"notes_attribute":1,"notes_level":1,"effect":1,"effect_value":0.079,"position":5},{"timing_sec":5.937,"notes_attribute":1,"notes_level":1,"effect":3,"effect_value":1.263,"position":3},{"timing_sec":7.516,"notes_attribute":1,"notes_level":1,"effect":1,"effect_value":0.079,"position":7},{"timing_sec":7.516,"notes_attribute":1,"notes_level":1,"effect":1,"effect_value":0.079,"position":3},{"timing_sec":8.147,"notes_attribute":1,"notes_level":1,"effect":2,"effect_value":0.079,"position":5},{"timing_sec":8.463,"notes_attribute":1,"notes_level":1,"effect":3,"effect_value":0.632,"position":7},{"timing_sec":8.463,"notes_attribute":1,"notes_level":1,"effect":4,"effect_value":0.079,"position":4},{"timing_sec":9.095,"notes_attribute":1,"notes_level":1,"effect":1,"effect_value":0.079,"position":3},{"timing_sec":9.726,"notes_attribute":1,"notes_level":1,"effect":3,"effect_value":0.632,"position":6},{"timing_sec":9.726,"notes_attribute":1,"notes_level":1,"effect":4,"effect_value":0.079,"position":3},{"timing_sec":10.358,"notes_attribute":1,"notes_level":1,"effect":1,"effect_value":0.079,"position":3},{"timing_sec":10.516,"notes_attribute":1,"notes_level":1,"effect":1,"effect_value":0.079,"position":4},{"timing_sec":10.674,"notes_attribute":1,"notes_level":1,"effect":1,"effect_value":0.079,"position":3},{"timing_sec":10.674,"notes_attribute":1,"notes_level":1,"effect":1,"effect_value":0.079,"position":6},{"timing_sec":10.989,"notes_attribute":1,"notes_level":1,"effect":1,"effect_value":0.079,"position":7},{"timing_sec":11.147,"notes_attribute":1,"notes_level":1,"effect":1,"effect_value":0.079,"position":6},{"timing_sec":11.305,"notes_attribute":1,"notes_level":1,"effect":1,"effect_value":0.079,"position":5},{"timing_sec":11.463,"notes_attribute":1,"notes_level":1,"effect":4,"effect_value":0.079,"position":7},{"timing_sec":11.463,"notes_attribute":1,"notes_level":1,"effect":1,"effect_value":0.079,"position":4},{"timing_sec":11.779,"notes_attribute":1,"notes_level":1,"effect":1,"effect_value":0.079,"position":4},{"timing_sec":11.937,"notes_attribute":1,"notes_level":1,"effect":1,"effect_value":0.079,"position":5},{"timing_sec":12.095,"notes_attribute":1,"notes_level":1,"effect":4,"effect_value":0.079,"position":3},{"timing_sec":12.095,"notes_attribute":1,"notes_level":1,"effect":1,"effect_value":0.079,"position":6},{"timing_sec":12.411,"notes_attribute":1,"notes_level":1,"effect":2,"effect_value":0.079,"position":5},{"timing_sec":12.726,"notes_attribute":1,"notes_level":1,"effect":1,"effect_value":0.079,"position":6},{"timing_sec":12.884,"notes_attribute":1,"notes_level":1,"effect":4,"effect_value":0.079,"position":5},{"timing_sec":13.042,"notes_attribute":1,"notes_level":1,"effect":4,"effect_value":0.079,"position":4},{"timing_sec":13.2,"notes_attribute":1,"notes_level":1,"effect":4,"effect_value":0.079,"position":3},{"timing_sec":13.2,"notes_attribute":1,"notes_level":1,"effect":4,"effect_value":0.079,"position":7},{"timing_sec":13.516,"notes_attribute":1,"notes_level":1,"effect":1,"effect_value":0.079,"position":5},{"timing_sec":13.674,"notes_attribute":1,"notes_level":1,"effect":1,"effect_value":0.079,"position":5},{"timing_sec":13.832,"notes_attribute":1,"notes_level":1,"effect":1,"effect_value":0.079,"position":6},{"timing_sec":13.832,"notes_attribute":1,"notes_level":1,"effect":1,"effect_value":0.079,"position":4},{"timing_sec":14.147,"notes_attribute":1,"notes_level":1,"effect":3,"effect_value":0.316,"position":3},{"timing_sec":14.147,"notes_attribute":1,"notes_level":1,"effect":1,"effect_value":0.079,"position":7},{"timing_sec":14.463,"notes_attribute":1,"notes_level":1,"effect":1,"effect_value":0.079,"position":7},{"timing_sec":14.621,"notes_attribute":1,"notes_level":1,"effect":1,"effect_value":0.079,"position":5},{"timing_sec":14.779,"notes_attribute":1,"notes_level":1,"effect":1,"effect_value":0.079,"position":6},{"timing_sec":14.937,"notes_attribute":1,"notes_level":1,"effect":1,"effect_value":0.079,"position":4},{"timing_sec":15.095,"notes_attribute":1,"notes_level":1,"effect":1,"effect_value":0.079,"position":5},{"timing_sec":15.253,"notes_attribute":1,"notes_level":1,"effect":1,"effect_value":0.079,"position":3},{"timing_sec":15.411,"notes_attribute":1,"notes_level":1,"effect":3,"effect_value":0.158,"position":4},{"timing_sec":15.726,"notes_attribute":1,"notes_level":1,"effect":4,"effect_value":0.079,"position":5},{"timing_sec":15.726,"notes_attribute":1,"notes_level":1,"effect":1,"effect_value":0.079,"position":3},{"timing_sec":15.884,"notes_attribute":1,"notes_level":1,"effect":1,"effect_value":0.079,"position":4},{"timing_sec":15.963,"notes_attribute":1,"notes_level":1,"effect":1,"effect_value":0.079,"position":6},{"timing_sec":16.042,"notes_attribute":1,"notes_level":1,"effect":2,"effect_value":0.079,"position":4},{"timing_sec":16.2,"notes_attribute":1,"notes_level":1,"effect":1,"effect_value":0.079,"position":5},{"timing_sec":16.358,"notes_attribute":1,"notes_level":1,"effect":1,"effect_value":0.079,"position":4},{"timing_sec":16.358,"notes_attribute":1,"notes_level":1,"effect":1,"effect_value":0.079,"position":6},{"timing_sec":16.674,"notes_attribute":1,"notes_level":1,"effect":3,"effect_value":0.316,"position":7},{"timing_sec":16.674,"notes_attribute":1,"notes_level":1,"effect":1,"effect_value":0.079,"position":3},{"timing_sec":16.989,"notes_attribute":1,"notes_level":1,"effect":1,"effect_value":0.079,"position":3},{"timing_sec":17.147,"notes_attribute":1,"notes_level":1,"effect":1,"effect_value":0.079,"position":5},{"timing_sec":17.305,"notes_attribute":1,"notes_level":1,"effect":1,"effect_value":0.079,"position":4},{"timing_sec":17.463,"notes_attribute":1,"notes_level":1,"effect":1,"effect_value":0.079,"position":6},{"timing_sec":17.621,"notes_attribute":1,"notes_level":1,"effect":1,"effect_value":0.079,"position":5},{"timing_sec":17.779,"notes_attribute":1,"notes_level":1,"effect":1,"effect_value":0.079,"position":7},{"timing_sec":17.937,"notes_attribute":1,"notes_level":1,"effect":3,"effect_value":0.158,"position":6},{"timing_sec":18.253,"notes_attribute":1,"notes_level":1,"effect":4,"effect_value":0.079,"position":5},{"timing_sec":18.253,"notes_attribute":1,"notes_level":1,"effect":1,"effect_value":0.079,"position":7},{"timing_sec":18.41,"notes_attribute":1,"notes_level":1,"effect":1,"effect_value":0.079,"position":6},{"timing_sec":18.489,"notes_attribute":1,"notes_level":1,"effect":1,"effect_value":0.079,"position":4},{"timing_sec":18.568,"notes_attribute":1,"notes_level":1,"effect":1,"effect_value":0.079,"position":6},{"timing_sec":18.726,"notes_attribute":1,"notes_level":1,"effect":1,"effect_value":0.079,"position":5},{"timing_sec":18.884,"notes_attribute":1,"notes_level":1,"effect":1,"effect_value":0.079,"position":4},{"timing_sec":18.884,"notes_attribute":1,"notes_level":1,"effect":1,"effect_value":0.079,"position":6},{"timing_sec":19.2,"notes_attribute":1,"notes_level":1,"effect":3,"effect_value":0.316,"position":3},{"timing_sec":19.2,"notes_attribute":1,"notes_level":1,"effect":1,"effect_value":0.079,"position":7},{"timing_sec":19.516,"notes_attribute":1,"notes_level":1,"effect":1,"effect_value":0.079,"position":7},{"timing_sec":19.674,"notes_attribute":1,"notes_level":1,"effect":1,"effect_value":0.079,"position":5},{"timing_sec":19.832,"notes_attribute":1,"notes_level":1,"effect":2,"effect_value":0.079,"position":6},{"timing_sec":19.989,"notes_attribute":1,"notes_level":1,"effect":1,"effect_value":0.079,"position":4},{"timing_sec":20.147,"notes_attribute":1,"notes_level":1,"effect":1,"effect_value":0.079,"position":5},{"timing_sec":20.305,"notes_attribute":1,"notes_level":1,"effect":1,"effect_value":0.079,"position":3},{"timing_sec":20.463,"notes_attribute":1,"notes_level":1,"effect":1,"effect_value":0.079,"position":4},{"timing_sec":20.463,"notes_attribute":1,"notes_level":1,"effect":1,"effect_value":0.079,"position":6},{"timing_sec":20.779,"notes_attribute":1,"notes_level":1,"effect":4,"effect_value":0.079,"position":3},{"timing_sec":20.779,"notes_attribute":1,"notes_level":1,"effect":4,"effect_value":0.079,"position":7},{"timing_sec":21.095,"notes_attribute":1,"notes_level":1,"effect":1,"effect_value":0.079,"position":7},{"timing_sec":21.095,"notes_attribute":1,"notes_level":1,"effect":1,"effect_value":0.079,"position":5},{"timing_sec":21.253,"notes_attribute":1,"notes_level":1,"effect":1,"effect_value":0.079,"position":3},{"timing_sec":21.41,"notes_attribute":1,"notes_level":1,"effect":1,"effect_value":0.079,"position":4},{"timing_sec":21.568,"notes_attribute":1,"notes_level":1,"effect":4,"effect_value":0.079,"position":3},{"timing_sec":21.568,"notes_attribute":1,"notes_level":1,"effect":1,"effect_value":0.079,"position":6},{"timing_sec":21.884,"notes_attribute":1,"notes_level":1,"effect":1,"effect_value":0.079,"position":5},{"timing_sec":21.884,"notes_attribute":1,"notes_level":1,"effect":1,"effect_value":0.079,"position":3},{"timing_sec":22.042,"notes_attribute":1,"notes_level":1,"effect":1,"effect_value":0.079,"position":7},{"timing_sec":22.2,"notes_attribute":1,"notes_level":1,"effect":4,"effect_value":0.079,"position":6},{"timing_sec":22.2,"notes_attribute":1,"notes_level":1,"effect":1,"effect_value":0.079,"position":4},{"timing_sec":22.516,"notes_attribute":1,"notes_level":1,"effect":1,"effect_value":0.079,"position":5},{"timing_sec":22.516,"notes_attribute":1,"notes_level":1,"effect":1,"effect_value":0.079,"position":7},{"timing_sec":22.674,"notes_attribute":1,"notes_level":1,"effect":1,"effect_value":0.079,"position":3},{"timing_sec":22.832,"notes_attribute":1,"notes_level":1,"effect":4,"effect_value":0.079,"position":4},{"timing_sec":22.832,"notes_attribute":1,"notes_level":1,"effect":1,"effect_value":0.079,"position":6},{"timing_sec":23.147,"notes_attribute":1,"notes_level":1,"effect":4,"effect_value":0.079,"position":7},{"timing_sec":23.147,"notes_attribute":1,"notes_level":1,"effect":1,"effect_value":0.079,"position":3},{"timing_sec":23.305,"notes_attribute":1,"notes_level":1,"effect":4,"effect_value":0.079,"position":6},{"timing_sec":23.305,"notes_attribute":1,"notes_level":1,"effect":1,"effect_value":0.079,"position":4},{"timing_sec":23.463,"notes_attribute":1,"notes_level":1,"effect":3,"effect_value":1.421,"position":7},{"timing_sec":23.463,"notes_attribute":1,"notes_level":1,"effect":4,"effect_value":0.079,"position":3},{"timing_sec":24.884,"notes_attribute":1,"notes_level":1,"effect":1,"effect_value":0.079,"position":3},{"timing_sec":26.147,"notes_attribute":1,"notes_level":1,"effect":3,"effect_value":0.947,"position":3},{"timing_sec":26.463,"notes_attribute":1,"notes_level":1,"effect":1,"effect_value":0.079,"position":5},{"timing_sec":26.779,"notes_attribute":1,"notes_level":1,"effect":1,"effect_value":0.079,"position":6},{"timing_sec":27.095,"notes_attribute":1,"notes_level":1,"effect":1,"effect_value":0.079,"position":7},{"timing_sec":27.41,"notes_attribute":1,"notes_level":1,"effect":3,"effect_value":0.316,"position":6},{"timing_sec":27.726,"notes_attribute":1,"notes_level":1,"effect":2,"effect_value":0.079,"position":4},{"timing_sec":27.884,"notes_attribute":1,"notes_level":1,"effect":3,"effect_value":0.474,"position":7},{"timing_sec":28.358,"notes_attribute":1,"notes_level":1,"effect":4,"effect_value":0.079,"position":5},{"timing_sec":28.516,"notes_attribute":1,"notes_level":1,"effect":1,"effect_value":0.079,"position":5},{"timing_sec":28.674,"notes_attribute":1,"notes_level":1,"effect":3,"effect_value":0.947,"position":7},{"timing_sec":28.989,"notes_attribute":1,"notes_level":1,"effect":1,"effect_value":0.079,"position":5},{"timing_sec":29.305,"notes_attribute":1,"notes_level":1,"effect":1,"effect_value":0.079,"position":4},{"timing_sec":29.621,"notes_attribute":1,"notes_level":1,"effect":1,"effect_value":0.079,"position":3},{"timing_sec":29.937,"notes_attribute":1,"notes_level":1,"effect":3,"effect_value":0.316,"position":4},{"timing_sec":30.253,"notes_attribute":1,"notes_level":1,"effect":1,"effect_value":0.079,"position":6},{"timing_sec":30.41,"notes_attribute":1,"notes_level":1,"effect":3,"effect_value":0.474,"position":3},{"timing_sec":30.884,"notes_attribute":1,"notes_level":1,"effect":4,"effect_value":0.079,"position":5},{"timing_sec":31.042,"notes_attribute":1,"notes_level":1,"effect":1,"effect_value":0.079,"position":5},{"timing_sec":31.2,"notes_attribute":1,"notes_level":1,"effect":3,"effect_value":1.263,"position":7},{"timing_sec":31.516,"notes_attribute":1,"notes_level":1,"effect":3,"effect_value":0.316,"position":4},{"timing_sec":32.147,"notes_attribute":1,"notes_level":1,"effect":3,"effect_value":0.947,"position":3},{"timing_sec":32.779,"notes_attribute":1,"notes_level":1,"effect":3,"effect_value":0.316,"position":5},{"timing_sec":33.41,"notes_attribute":1,"notes_level":1,"effect":2,"effect_value":0.079,"position":6},{"timing_sec":33.568,"notes_attribute":1,"notes_level":1,"effect":1,"effect_value":0.079,"position":6},{"timing_sec":33.726,"notes_attribute":1,"notes_level":1,"effect":3,"effect_value":1.263,"position":3},{"timing_sec":34.042,"notes_attribute":1,"notes_level":1,"effect":3,"effect_value":0.316,"position":6},{"timing_sec":34.674,"notes_attribute":1,"notes_level":1,"effect":3,"effect_value":0.947,"position":7},{"timing_sec":35.305,"notes_attribute":1,"notes_level":1,"effect":3,"effect_value":0.316,"position":5},{"timing_sec":35.779,"notes_attribute":1,"notes_level":1,"effect":1,"effect_value":0.079,"position":4},{"timing_sec":35.779,"notes_attribute":1,"notes_level":1,"effect":2,"effect_value":0.079,"position":7},{"timing_sec":35.937,"notes_attribute":1,"notes_level":1,"effect":1,"effect_value":0.079,"position":3},{"timing_sec":35.937,"notes_attribute":1,"notes_level":1,"effect":1,"effect_value":0.079,"position":6},{"timing_sec":36.253,"notes_attribute":1,"notes_level":1,"effect":4,"effect_value":0.079,"position":3},{"timing_sec":36.253,"notes_attribute":1,"notes_level":1,"effect":1,"effect_value":0.079,"position":7},{"timing_sec":36.568,"notes_attribute":1,"notes_level":1,"effect":1,"effect_value":0.079,"position":4},{"timing_sec":36.726,"notes_attribute":1,"notes_level":1,"effect":4,"effect_value":0.079,"position":3},{"timing_sec":36.726,"notes_attribute":1,"notes_level":1,"effect":1,"effect_value":0.079,"position":6},{"timing_sec":37.042,"notes_attribute":1,"notes_level":1,"effect":1,"effect_value":0.079,"position":6},{"timing_sec":37.2,"notes_attribute":1,"notes_level":1,"effect":4,"effect_value":0.079,"position":4},{"timing_sec":37.2,"notes_attribute":1,"notes_level":1,"effect":1,"effect_value":0.079,"position":7},{"timing_sec":37.674,"notes_attribute":1,"notes_level":1,"effect":1,"effect_value":0.079,"position":5},{"timing_sec":37.832,"notes_attribute":1,"notes_level":1,"effect":1,"effect_value":0.079,"position":3},{"timing_sec":37.832,"notes_attribute":1,"notes_level":1,"effect":1,"effect_value":0.079,"position":7},{"timing_sec":38.147,"notes_attribute":1,"notes_level":1,"effect":1,"effect_value":0.079,"position":6},{"timing_sec":38.305,"notes_attribute":1,"notes_level":1,"effect":1,"effect_value":0.079,"position":4},{"timing_sec":38.463,"notes_attribute":1,"notes_level":1,"effect":1,"effect_value":0.079,"position":3},{"timing_sec":38.463,"notes_attribute":1,"notes_level":1,"effect":1,"effect_value":0.079,"position":7},{"timing_sec":38.779,"notes_attribute":1,"notes_level":1,"effect":4,"effect_value":0.079,"position":7},{"timing_sec":38.779,"notes_attribute":1,"notes_level":1,"effect":1,"effect_value":0.079,"position":3},{"timing_sec":39.095,"notes_attribute":1,"notes_level":1,"effect":1,"effect_value":0.079,"position":6},{"timing_sec":39.253,"notes_attribute":1,"notes_level":1,"effect":4,"effect_value":0.079,"position":7},{"timing_sec":39.253,"notes_attribute":1,"notes_level":1,"effect":1,"effect_value":0.079,"position":4},{"timing_sec":39.568,"notes_attribute":1,"notes_level":1,"effect":2,"effect_value":0.079,"position":4},{"timing_sec":39.726,"notes_attribute":1,"notes_level":1,"effect":4,"effect_value":0.079,"position":6},{"timing_sec":39.726,"notes_attribute":1,"notes_level":1,"effect":1,"effect_value":0.079,"position":3},{"timing_sec":40.2,"notes_attribute":1,"notes_level":1,"effect":1,"effect_value":0.079,"position":5},{"timing_sec":40.358,"notes_attribute":1,"notes_level":1,"effect":1,"effect_value":0.079,"position":7},{"timing_sec":40.358,"notes_attribute":1,"notes_level":1,"effect":1,"effect_value":0.079,"position":3},{"timing_sec":40.674,"notes_attribute":1,"notes_level":1,"effect":4,"effect_value":0.079,"position":4},{"timing_sec":40.674,"notes_attribute":1,"notes_level":1,"effect":1,"effect_value":0.079,"position":6},{"timing_sec":40.832,"notes_attribute":1,"notes_level":1,"effect":4,"effect_value":0.079,"position":4},{"timing_sec":40.832,"notes_attribute":1,"notes_level":1,"effect":1,"effect_value":0.079,"position":6},{"timing_sec":40.989,"notes_attribute":1,"notes_level":1,"effect":4,"effect_value":0.079,"position":7},{"timing_sec":40.989,"notes_attribute":1,"notes_level":1,"effect":1,"effect_value":0.079,"position":3},{"timing_sec":41.305,"notes_attribute":1,"notes_level":1,"effect":1,"effect_value":0.079,"position":6},{"timing_sec":41.463,"notes_attribute":1,"notes_level":1,"effect":1,"effect_value":0.079,"position":4},{"timing_sec":41.621,"notes_attribute":1,"notes_level":1,"effect":3,"effect_value":0.316,"position":7},{"timing_sec":41.937,"notes_attribute":1,"notes_level":1,"effect":1,"effect_value":0.079,"position":5},{"timing_sec":42.095,"notes_attribute":1,"notes_level":1,"effect":1,"effect_value":0.079,"position":5},{"timing_sec":42.253,"notes_attribute":1,"notes_level":1,"effect":3,"effect_value":0.316,"position":6},{"timing_sec":42.568,"notes_attribute":1,"notes_level":1,"effect":4,"effect_value":0.079,"position":4},{"timing_sec":42.726,"notes_attribute":1,"notes_level":1,"effect":1,"effect_value":0.079,"position":6},{"timing_sec":42.884,"notes_attribute":1,"notes_level":1,"effect":1,"effect_value":0.079,"position":7},{"timing_sec":43.042,"notes_attribute":1,"notes_level":1,"effect":1,"effect_value":0.079,"position":6},{"timing_sec":43.2,"notes_attribute":1,"notes_level":1,"effect":1,"effect_value":0.079,"position":5},{"timing_sec":43.358,"notes_attribute":1,"notes_level":1,"effect":1,"effect_value":0.079,"position":4},{"timing_sec":43.516,"notes_attribute":1,"notes_level":1,"effect":1,"effect_value":0.079,"position":7},{"timing_sec":43.516,"notes_attribute":1,"notes_level":1,"effect":1,"effect_value":0.079,"position":3},{"timing_sec":43.832,"notes_attribute":1,"notes_level":1,"effect":2,"effect_value":0.079,"position":4},{"timing_sec":43.989,"notes_attribute":1,"notes_level":1,"effect":1,"effect_value":0.079,"position":6},{"timing_sec":44.147,"notes_attribute":1,"notes_level":1,"effect":3,"effect_value":0.316,"position":3},{"timing_sec":44.463,"notes_attribute":1,"notes_level":1,"effect":1,"effect_value":0.079,"position":5},{"timing_sec":44.621,"notes_attribute":1,"notes_level":1,"effect":1,"effect_value":0.079,"position":5},{"timing_sec":44.779,"notes_attribute":1,"notes_level":1,"effect":3,"effect_value":0.316,"position":4},{"timing_sec":45.095,"notes_attribute":1,"notes_level":1,"effect":4,"effect_value":0.079,"position":6},{"timing_sec":45.253,"notes_attribute":1,"notes_level":1,"effect":1,"effect_value":0.079,"position":4},{"timing_sec":45.41,"notes_attribute":1,"notes_level":1,"effect":1,"effect_value":0.079,"position":3},{"timing_sec":45.568,"notes_attribute":1,"notes_level":1,"effect":1,"effect_value":0.079,"position":4},{"timing_sec":45.726,"notes_attribute":1,"notes_level":1,"effect":1,"effect_value":0.079,"position":5},{"timing_sec":45.884,"notes_attribute":1,"notes_level":1,"effect":1,"effect_value":0.079,"position":6},{"timing_sec":46.042,"notes_attribute":1,"notes_level":1,"effect":1,"effect_value":0.079,"position":3},{"timing_sec":46.042,"notes_attribute":1,"notes_level":1,"effect":1,"effect_value":0.079,"position":7},{"timing_sec":46.358,"notes_attribute":1,"notes_level":1,"effect":1,"effect_value":0.079,"position":6},{"timing_sec":46.516,"notes_attribute":1,"notes_level":1,"effect":1,"effect_value":0.079,"position":7},{"timing_sec":46.674,"notes_attribute":1,"notes_level":1,"effect":1,"effect_value":0.079,"position":6},{"timing_sec":46.832,"notes_attribute":1,"notes_level":1,"effect":1,"effect_value":0.079,"position":5},{"timing_sec":46.989,"notes_attribute":1,"notes_level":1,"effect":3,"effect_value":0.158,"position":4},{"timing_sec":47.147,"notes_attribute":1,"notes_level":1,"effect":1,"effect_value":0.079,"position":6},{"timing_sec":47.305,"notes_attribute":1,"notes_level":1,"effect":1,"effect_value":0.079,"position":3},{"timing_sec":47.305,"notes_attribute":1,"notes_level":1,"effect":1,"effect_value":0.079,"position":7},{"timing_sec":47.621,"notes_attribute":1,"notes_level":1,"effect":1,"effect_value":0.079,"position":4},{"timing_sec":47.779,"notes_attribute":1,"notes_level":1,"effect":2,"effect_value":0.079,"position":3},{"timing_sec":47.937,"notes_attribute":1,"notes_level":1,"effect":1,"effect_value":0.079,"position":4},{"timing_sec":48.095,"notes_attribute":1,"notes_level":1,"effect":1,"effect_value":0.079,"position":5},{"timing_sec":48.253,"notes_attribute":1,"notes_level":1,"effect":3,"effect_value":0.158,"position":6},{"timing_sec":48.41,"notes_attribute":1,"notes_level":1,"effect":1,"effect_value":0.079,"position":4},{"timing_sec":48.568,"notes_attribute":1,"notes_level":1,"effect":1,"effect_value":0.079,"position":7},{"timing_sec":48.568,"notes_attribute":1,"notes_level":1,"effect":1,"effect_value":0.079,"position":3},{"timing_sec":48.884,"notes_attribute":1,"notes_level":1,"effect":3,"effect_value":0.158,"position":6},{"timing_sec":49.042,"notes_attribute":1,"notes_level":1,"effect":1,"effect_value":0.079,"position":4},{"timing_sec":49.2,"notes_attribute":1,"notes_level":1,"effect":1,"effect_value":0.079,"position":3},{"timing_sec":49.2,"notes_attribute":1,"notes_level":1,"effect":1,"effect_value":0.079,"position":7},{"timing_sec":49.516,"notes_attribute":1,"notes_level":1,"effect":3,"effect_value":0.158,"position":4},{"timing_sec":49.674,"notes_attribute":1,"notes_level":1,"effect":1,"effect_value":0.079,"position":6},{"timing_sec":49.832,"notes_attribute":1,"notes_level":1,"effect":1,"effect_value":0.079,"position":7},{"timing_sec":49.832,"notes_attribute":1,"notes_level":1,"effect":1,"effect_value":0.079,"position":3},{"timing_sec":50.147,"notes_attribute":1,"notes_level":1,"effect":1,"effect_value":0.079,"position":3},{"timing_sec":50.305,"notes_attribute":1,"notes_level":1,"effect":1,"effect_value":0.079,"position":4},{"timing_sec":50.463,"notes_attribute":1,"notes_level":1,"effect":1,"effect_value":0.079,"position":5},{"timing_sec":50.621,"notes_attribute":1,"notes_level":1,"effect":1,"effect_value":0.079,"position":6},{"timing_sec":50.779,"notes_attribute":1,"notes_level":1,"effect":1,"effect_value":0.079,"position":7},{"timing_sec":50.937,"notes_attribute":1,"notes_level":1,"effect":1,"effect_value":0.079,"position":5},{"timing_sec":51.095,"notes_attribute":1,"notes_level":1,"effect":1,"effect_value":0.079,"position":4},{"timing_sec":51.095,"notes_attribute":1,"notes_level":1,"effect":1,"effect_value":0.079,"position":6},{"timing_sec":51.253,"notes_attribute":1,"notes_level":1,"effect":1,"effect_value":0.079,"position":4},{"timing_sec":51.253,"notes_attribute":1,"notes_level":1,"effect":1,"effect_value":0.079,"position":6},{"timing_sec":51.41,"notes_attribute":1,"notes_level":1,"effect":3,"effect_value":0.158,"position":7},{"timing_sec":51.568,"notes_attribute":1,"notes_level":1,"effect":3,"effect_value":0.158,"position":4},{"timing_sec":51.726,"notes_attribute":1,"notes_level":1,"effect":3,"effect_value":0.158,"position":6},{"timing_sec":51.884,"notes_attribute":1,"notes_level":1,"effect":3,"effect_value":0.474,"position":3},{"timing_sec":52.358,"notes_attribute":1,"notes_level":1,"effect":4,"effect_value":0.079,"position":6},{"timing_sec":52.516,"notes_attribute":1,"notes_level":1,"effect":2,"effect_value":0.079,"position":7},{"timing_sec":52.674,"notes_attribute":1,"notes_level":1,"effect":3,"effect_value":0.158,"position":4},{"timing_sec":52.831,"notes_attribute":1,"notes_level":1,"effect":3,"effect_value":0.158,"position":6},{"timing_sec":52.989,"notes_attribute":1,"notes_level":1,"effect":3,"effect_value":0.158,"position":4},{"timing_sec":53.147,"notes_attribute":1,"notes_level":1,"effect":3,"effect_value":0.474,"position":6},{"timing_sec":53.621,"notes_attribute":1,"notes_level":1,"effect":4,"effect_value":0.079,"position":3},{"timing_sec":53.779,"notes_attribute":1,"notes_level":1,"effect":1,"effect_value":0.079,"position":4},{"timing_sec":53.937,"notes_attribute":1,"notes_level":1,"effect":1,"effect_value":0.079,"position":6},{"timing_sec":54.095,"notes_attribute":1,"notes_level":1,"effect":1,"effect_value":0.079,"position":7},{"timing_sec":54.253,"notes_attribute":1,"notes_level":1,"effect":1,"effect_value":0.079,"position":6},{"timing_sec":54.41,"notes_attribute":1,"notes_level":1,"effect":3,"effect_value":0.316,"position":5},{"timing_sec":54.884,"notes_attribute":1,"notes_level":1,"effect":1,"effect_value":0.079,"position":7},{"timing_sec":54.884,"notes_attribute":1,"notes_level":1,"effect":1,"effect_value":0.079,"position":3},{"timing_sec":55.2,"notes_attribute":1,"notes_level":1,"effect":1,"effect_value":0.079,"position":4},{"timing_sec":55.358,"notes_attribute":1,"notes_level":1,"effect":1,"effect_value":0.079,"position":3},{"timing_sec":55.516,"notes_attribute":1,"notes_level":1,"effect":1,"effect_value":0.079,"position":4},{"timing_sec":55.674,"notes_attribute":1,"notes_level":1,"effect":3,"effect_value":0.316,"position":5},{"timing_sec":56.147,"notes_attribute":1,"notes_level":1,"effect":2,"effect_value":0.079,"position":4},{"timing_sec":56.147,"notes_attribute":1,"notes_level":1,"effect":1,"effect_value":0.079,"position":6},{"timing_sec":56.463,"notes_attribute":1,"notes_level":1,"effect":3,"effect_value":0.158,"position":3},{"timing_sec":56.621,"notes_attribute":1,"notes_level":1,"effect":3,"effect_value":0.158,"position":6},{"timing_sec":56.779,"notes_attribute":1,"notes_level":1,"effect":3,"effect_value":0.158,"position":4},{"timing_sec":56.937,"notes_attribute":1,"notes_level":1,"effect":3,"effect_value":0.474,"position":7},{"timing_sec":57.41,"notes_attribute":1,"notes_level":1,"effect":4,"effect_value":0.079,"position":4},{"timing_sec":57.568,"notes_attribute":1,"notes_level":1,"effect":1,"effect_value":0.079,"position":3},{"timing_sec":57.726,"notes_attribute":1,"notes_level":1,"effect":3,"effect_value":0.158,"position":6},{"timing_sec":57.884,"notes_attribute":1,"notes_level":1,"effect":3,"effect_value":0.158,"position":4},{"timing_sec":58.042,"notes_attribute":1,"notes_level":1,"effect":3,"effect_value":0.158,"position":6},{"timing_sec":58.2,"notes_attribute":1,"notes_level":1,"effect":3,"effect_value":0.474,"position":4},{"timing_sec":58.674,"notes_attribute":1,"notes_level":1,"effect":4,"effect_value":0.079,"position":7},{"timing_sec":58.831,"notes_attribute":1,"notes_level":1,"effect":1,"effect_value":0.079,"position":6},{"timing_sec":58.989,"notes_attribute":1,"notes_level":1,"effect":1,"effect_value":0.079,"position":3},{"timing_sec":59.147,"notes_attribute":1,"notes_level":1,"effect":1,"effect_value":0.079,"position":7},{"timing_sec":59.305,"notes_attribute":1,"notes_level":1,"effect":1,"effect_value":0.079,"position":6},{"timing_sec":59.463,"notes_attribute":1,"notes_level":1,"effect":3,"effect_value":0.316,"position":4},{"timing_sec":59.937,"notes_attribute":1,"notes_level":1,"effect":1,"effect_value":0.079,"position":3},{"timing_sec":59.937,"notes_attribute":1,"notes_level":1,"effect":1,"effect_value":0.079,"position":7},{"timing_sec":60.253,"notes_attribute":1,"notes_level":1,"effect":2,"effect_value":0.079,"position":7},{"timing_sec":60.41,"notes_attribute":1,"notes_level":1,"effect":1,"effect_value":0.079,"position":5},{"timing_sec":60.568,"notes_attribute":1,"notes_level":1,"effect":1,"effect_value":0.079,"position":6},{"timing_sec":60.726,"notes_attribute":1,"notes_level":1,"effect":1,"effect_value":0.079,"position":4},{"timing_sec":60.884,"notes_attribute":1,"notes_level":1,"effect":1,"effect_value":0.079,"position":5},{"timing_sec":61.042,"notes_attribute":1,"notes_level":1,"effect":1,"effect_value":0.079,"position":3},{"timing_sec":61.2,"notes_attribute":1,"notes_level":1,"effect":1,"effect_value":0.079,"position":6},{"timing_sec":61.2,"notes_attribute":1,"notes_level":1,"effect":1,"effect_value":0.079,"position":4},{"timing_sec":61.516,"notes_attribute":1,"notes_level":1,"effect":4,"effect_value":0.079,"position":7},{"timing_sec":61.516,"notes_attribute":1,"notes_level":1,"effect":1,"effect_value":0.079,"position":3},{"timing_sec":61.831,"notes_attribute":1,"notes_level":1,"effect":1,"effect_value":0.079,"position":7},{"timing_sec":61.989,"notes_attribute":1,"notes_level":1,"effect":1,"effect_value":0.079,"position":6},{"timing_sec":62.147,"notes_attribute":1,"notes_level":1,"effect":1,"effect_value":0.079,"position":5},{"timing_sec":62.305,"notes_attribute":1,"notes_level":1,"effect":1,"effect_value":0.079,"position":4},{"timing_sec":62.463,"notes_attribute":1,"notes_level":1,"effect":1,"effect_value":0.079,"position":3},{"timing_sec":62.463,"notes_attribute":1,"notes_level":1,"effect":1,"effect_value":0.079,"position":6},{"timing_sec":62.779,"notes_attribute":1,"notes_level":1,"effect":1,"effect_value":0.079,"position":4},{"timing_sec":62.779,"notes_attribute":1,"notes_level":1,"effect":1,"effect_value":0.079,"position":6},{"timing_sec":62.937,"notes_attribute":1,"notes_level":1,"effect":1,"effect_value":0.079,"position":7},{"timing_sec":62.937,"notes_attribute":1,"notes_level":1,"effect":1,"effect_value":0.079,"position":3},{"timing_sec":63.253,"notes_attribute":1,"notes_level":1,"effect":3,"effect_value":0.316,"position":4},{"timing_sec":63.253,"notes_attribute":1,"notes_level":1,"effect":3,"effect_value":0.316,"position":6},{"timing_sec":63.726,"notes_attribute":1,"notes_level":1,"effect":2,"effect_value":0.079,"position":7},{"timing_sec":63.726,"notes_attribute":1,"notes_level":1,"effect":1,"effect_value":0.079,"position":3},{"timing_sec":64.042,"notes_attribute":1,"notes_level":1,"effect":3,"effect_value":0.158,"position":3},{"timing_sec":64.2,"notes_attribute":1,"notes_level":1,"effect":3,"effect_value":0.158,"position":6},{"timing_sec":64.358,"notes_attribute":1,"notes_level":1,"effect":3,"effect_value":0.158,"position":4},{"timing_sec":64.516,"notes_attribute":1,"notes_level":1,"effect":3,"effect_value":0.158,"position":7},{"timing_sec":64.674,"notes_attribute":1,"notes_level":1,"effect":3,"effect_value":0.158,"position":5},{"timing_sec":64.831,"notes_attribute":1,"notes_level":1,"effect":1,"effect_value":0.079,"position":7},{"timing_sec":64.989,"notes_attribute":1,"notes_level":1,"effect":1,"effect_value":0.079,"position":3},{"timing_sec":64.989,"notes_attribute":1,"notes_level":1,"effect":1,"effect_value":0.079,"position":7},{"timing_sec":65.305,"notes_attribute":1,"notes_level":1,"effect":1,"effect_value":0.079,"position":3},{"timing_sec":65.305,"notes_attribute":1,"notes_level":1,"effect":1,"effect_value":0.079,"position":5},{"timing_sec":65.463,"notes_attribute":1,"notes_level":1,"effect":1,"effect_value":0.079,"position":3},{"timing_sec":65.463,"notes_attribute":1,"notes_level":1,"effect":1,"effect_value":0.079,"position":5},{"timing_sec":65.779,"notes_attribute":1,"notes_level":1,"effect":1,"effect_value":0.079,"position":7},{"timing_sec":65.779,"notes_attribute":1,"notes_level":1,"effect":1,"effect_value":0.079,"position":5},{"timing_sec":65.937,"notes_attribute":1,"notes_level":1,"effect":1,"effect_value":0.079,"position":7},{"timing_sec":65.937,"notes_attribute":1,"notes_level":1,"effect":1,"effect_value":0.079,"position":5},{"timing_sec":66.253,"notes_attribute":1,"notes_level":1,"effect":4,"effect_value":0.079,"position":6},{"timing_sec":66.253,"notes_attribute":1,"notes_level":1,"effect":4,"effect_value":0.079,"position":4},{"timing_sec":66.41,"notes_attribute":1,"notes_level":1,"effect":4,"effect_value":0.079,"position":7},{"timing_sec":66.41,"notes_attribute":1,"notes_level":1,"effect":4,"effect_value":0.079,"position":3},{"timing_sec":66.884,"notes_attribute":1,"notes_level":1,"effect":3,"effect_value":0.316,"position":6},{"timing_sec":66.884,"notes_attribute":1,"notes_level":1,"effect":1,"effect_value":0.079,"position":4},{"timing_sec":67.2,"notes_attribute":1,"notes_level":1,"effect":3,"effect_value":0.316,"position":3},{"timing_sec":67.516,"notes_attribute":1,"notes_level":1,"effect":2,"effect_value":0.079,"position":7},{"timing_sec":67.831,"notes_attribute":1,"notes_level":1,"effect":3,"effect_value":0.947,"position":7},{"timing_sec":68.147,"notes_attribute":1,"notes_level":1,"effect":1,"effect_value":0.079,"position":3},{"timing_sec":68.463,"notes_attribute":1,"notes_level":1,"effect":1,"effect_value":0.079,"position":5},{"timing_sec":68.621,"notes_attribute":1,"notes_level":1,"effect":1,"effect_value":0.079,"position":4},{"timing_sec":68.779,"notes_attribute":1,"notes_level":1,"effect":1,"effect_value":0.079,"position":5},{"timing_sec":69.095,"notes_attribute":1,"notes_level":1,"effect":3,"effect_value":0.947,"position":3},{"timing_sec":69.41,"notes_attribute":1,"notes_level":1,"effect":1,"effect_value":0.079,"position":5},{"timing_sec":69.726,"notes_attribute":1,"notes_level":1,"effect":1,"effect_value":0.079,"position":7},{"timing_sec":69.884,"notes_attribute":1,"notes_level":1,"effect":1,"effect_value":0.079,"position":6},{"timing_sec":70.042,"notes_attribute":1,"notes_level":1,"effect":1,"effect_value":0.079,"position":7},{"timing_sec":70.358,"notes_attribute":1,"notes_level":1,"effect":4,"effect_value":0.079,"position":6},{"timing_sec":70.516,"notes_attribute":1,"notes_level":1,"effect":1,"effect_value":0.079,"position":4},{"timing_sec":70.674,"notes_attribute":1,"notes_level":1,"effect":3,"effect_value":0.316,"position":7},{"timing_sec":70.989,"notes_attribute":1,"notes_level":1,"effect":1,"effect_value":0.079,"position":4},{"timing_sec":71.147,"notes_attribute":1,"notes_level":1,"effect":1,"effect_value":0.079,"position":6},{"timing_sec":71.305,"notes_attribute":1,"notes_level":1,"effect":3,"effect_value":0.316,"position":3},{"timing_sec":71.621,"notes_attribute":1,"notes_level":1,"effect":4,"effect_value":0.079,"position":6},{"timing_sec":71.779,"notes_attribute":1,"notes_level":1,"effect":1,"effect_value":0.079,"position":4},{"timing_sec":71.937,"notes_attribute":1,"notes_level":1,"effect":3,"effect_value":0.316,"position":7},{"timing_sec":72.253,"notes_attribute":1,"notes_level":1,"effect":2,"effect_value":0.079,"position":5},{"timing_sec":72.41,"notes_attribute":1,"notes_level":1,"effect":1,"effect_value":0.079,"position":5},{"timing_sec":72.568,"notes_attribute":1,"notes_level":1,"effect":3,"effect_value":0.316,"position":6},{"timing_sec":72.884,"notes_attribute":1,"notes_level":1,"effect":3,"effect_value":0.947,"position":3},{"timing_sec":73.2,"notes_attribute":1,"notes_level":1,"effect":1,"effect_value":0.079,"position":7},{"timing_sec":73.516,"notes_attribute":1,"notes_level":1,"effect":1,"effect_value":0.079,"position":5},{"timing_sec":73.674,"notes_attribute":1,"notes_level":1,"effect":1,"effect_value":0.079,"position":6},{"timing_sec":73.831,"notes_attribute":1,"notes_level":1,"effect":1,"effect_value":0.079,"position":5},{"timing_sec":74.147,"notes_attribute":1,"notes_level":1,"effect":3,"effect_value":0.947,"position":7},{"timing_sec":74.463,"notes_attribute":1,"notes_level":1,"effect":1,"effect_value":0.079,"position":5},{"timing_sec":74.779,"notes_attribute":1,"notes_level":1,"effect":1,"effect_value":0.079,"position":3},{"timing_sec":74.937,"notes_attribute":1,"notes_level":1,"effect":1,"effect_value":0.079,"position":4},{"timing_sec":75.095,"notes_attribute":1,"notes_level":1,"effect":1,"effect_value":0.079,"position":3},{"timing_sec":75.41,"notes_attribute":1,"notes_level":1,"effect":4,"effect_value":0.079,"position":4},{"timing_sec":75.568,"notes_attribute":1,"notes_level":1,"effect":1,"effect_value":0.079,"position":6},{"timing_sec":75.726,"notes_attribute":1,"notes_level":1,"effect":2,"effect_value":0.079,"position":3},{"timing_sec":75.884,"notes_attribute":1,"notes_level":1,"effect":1,"effect_value":0.079,"position":3},{"timing_sec":75.884,"notes_attribute":1,"notes_level":1,"effect":1,"effect_value":0.079,"position":7},{"timing_sec":76.2,"notes_attribute":1,"notes_level":1,"effect":1,"effect_value":0.079,"position":6},{"timing_sec":76.2,"notes_attribute":1,"notes_level":1,"effect":1,"effect_value":0.079,"position":4},{"timing_sec":76.358,"notes_attribute":1,"notes_level":1,"effect":1,"effect_value":0.079,"position":5},{"timing_sec":76.516,"notes_attribute":1,"notes_level":1,"effect":4,"effect_value":0.079,"position":7},{"timing_sec":76.516,"notes_attribute":1,"notes_level":1,"effect":1,"effect_value":0.079,"position":3},{"timing_sec":76.831,"notes_attribute":1,"notes_level":1,"effect":4,"effect_value":0.079,"position":7},{"timing_sec":76.831,"notes_attribute":1,"notes_level":1,"effect":1,"effect_value":0.079,"position":5},{"timing_sec":77.147,"notes_attribute":1,"notes_level":1,"effect":4,"effect_value":0.079,"position":3},{"timing_sec":77.147,"notes_attribute":1,"notes_level":1,"effect":1,"effect_value":0.079,"position":5},{"timing_sec":77.463,"notes_attribute":1,"notes_level":1,"effect":4,"effect_value":0.079,"position":4},{"timing_sec":77.463,"notes_attribute":1,"notes_level":1,"effect":1,"effect_value":0.079,"position":6},{"timing_sec":77.621,"notes_attribute":1,"notes_level":1,"effect":1,"effect_value":0.079,"position":3},{"timing_sec":77.621,"notes_attribute":1,"notes_level":1,"effect":1,"effect_value":0.079,"position":7},{"timing_sec":77.937,"notes_attribute":1,"notes_level":1,"effect":3,"effect_value":0.316,"position":6},{"timing_sec":77.937,"notes_attribute":1,"notes_level":1,"effect":1,"effect_value":0.079,"position":3},{"timing_sec":78.253,"notes_attribute":1,"notes_level":1,"effect":1,"effect_value":0.079,"position":3},{"timing_sec":78.41,"notes_attribute":1,"notes_level":1,"effect":1,"effect_value":0.079,"position":4},{"timing_sec":78.568,"notes_attribute":1,"notes_level":1,"effect":1,"effect_value":0.079,"position":5},{"timing_sec":78.726,"notes_attribute":1,"notes_level":1,"effect":1,"effect_value":0.079,"position":4},{"timing_sec":78.884,"notes_attribute":1,"notes_level":1,"effect":1,"effect_value":0.079,"position":6},{"timing_sec":79.042,"notes_attribute":1,"notes_level":1,"effect":3,"effect_value":0.158,"position":7},{"timing_sec":79.2,"notes_attribute":1,"notes_level":1,"effect":1,"effect_value":0.079,"position":4},{"timing_sec":79.358,"notes_attribute":1,"notes_level":1,"effect":3,"effect_value":0.158,"position":6},{"timing_sec":79.516,"notes_attribute":1,"notes_level":1,"effect":2,"effect_value":0.079,"position":4},{"timing_sec":79.674,"notes_attribute":1,"notes_level":1,"effect":1,"effect_value":0.079,"position":3},{"timing_sec":79.831,"notes_attribute":1,"notes_level":1,"effect":1,"effect_value":0.079,"position":7},{"timing_sec":79.989,"notes_attribute":1,"notes_level":1,"effect":1,"effect_value":0.079,"position":6},{"timing_sec":80.147,"notes_attribute":1,"notes_level":1,"effect":1,"effect_value":0.079,"position":5},{"timing_sec":80.305,"notes_attribute":1,"notes_level":1,"effect":1,"effect_value":0.079,"position":4},{"timing_sec":80.384,"notes_attribute":1,"notes_level":1,"effect":1,"effect_value":0.079,"position":6},{"timing_sec":80.463,"notes_attribute":1,"notes_level":1,"effect":3,"effect_value":0.316,"position":4},{"timing_sec":80.779,"notes_attribute":1,"notes_level":1,"effect":1,"effect_value":0.079,"position":7},{"timing_sec":80.937,"notes_attribute":1,"notes_level":1,"effect":1,"effect_value":0.079,"position":6},{"timing_sec":81.095,"notes_attribute":1,"notes_level":1,"effect":1,"effect_value":0.079,"position":5},{"timing_sec":81.253,"notes_attribute":1,"notes_level":1,"effect":1,"effect_value":0.079,"position":6},{"timing_sec":81.41,"notes_attribute":1,"notes_level":1,"effect":1,"effect_value":0.079,"position":4},{"timing_sec":81.568,"notes_attribute":1,"notes_level":1,"effect":3,"effect_value":0.158,"position":3},{"timing_sec":81.726,"notes_attribute":1,"notes_level":1,"effect":1,"effect_value":0.079,"position":6},{"timing_sec":81.884,"notes_attribute":1,"notes_level":1,"effect":3,"effect_value":0.158,"position":4},{"timing_sec":82.042,"notes_attribute":1,"notes_level":1,"effect":1,"effect_value":0.079,"position":6},{"timing_sec":82.2,"notes_attribute":1,"notes_level":1,"effect":1,"effect_value":0.079,"position":7},{"timing_sec":82.358,"notes_attribute":1,"notes_level":1,"effect":1,"effect_value":0.079,"position":3},{"timing_sec":82.516,"notes_attribute":1,"notes_level":1,"effect":1,"effect_value":0.079,"position":4},{"timing_sec":82.674,"notes_attribute":1,"notes_level":1,"effect":1,"effect_value":0.079,"position":5},{"timing_sec":82.831,"notes_attribute":1,"notes_level":1,"effect":1,"effect_value":0.079,"position":6},{"timing_sec":82.91,"notes_attribute":1,"notes_level":1,"effect":1,"effect_value":0.079,"position":4},{"timing_sec":82.989,"notes_attribute":1,"notes_level":1,"effect":1,"effect_value":0.079,"position":6},{"timing_sec":83.147,"notes_attribute":1,"notes_level":1,"effect":1,"effect_value":0.079,"position":5},{"timing_sec":83.305,"notes_attribute":1,"notes_level":1,"effect":1,"effect_value":0.079,"position":4},{"timing_sec":83.463,"notes_attribute":1,"notes_level":1,"effect":3,"effect_value":0.316,"position":7},{"timing_sec":83.779,"notes_attribute":1,"notes_level":1,"effect":1,"effect_value":0.079,"position":3},{"timing_sec":83.937,"notes_attribute":1,"notes_level":1,"effect":1,"effect_value":0.079,"position":3},{"timing_sec":84.095,"notes_attribute":1,"notes_level":1,"effect":1,"effect_value":0.079,"position":4},{"timing_sec":84.174,"notes_attribute":1,"notes_level":1,"effect":1,"effect_value":0.079,"position":6},{"timing_sec":84.253,"notes_attribute":1,"notes_level":1,"effect":1,"effect_value":0.079,"position":4},{"timing_sec":84.41,"notes_attribute":1,"notes_level":1,"effect":1,"effect_value":0.079,"position":5},{"timing_sec":84.568,"notes_attribute":1,"notes_level":1,"effect":1,"effect_value":0.079,"position":6},{"timing_sec":84.726,"notes_attribute":1,"notes_level":1,"effect":3,"effect_value":0.316,"position":3},{"timing_sec":85.042,"notes_attribute":1,"notes_level":1,"effect":1,"effect_value":0.079,"position":7},{"timing_sec":85.2,"notes_attribute":1,"notes_level":1,"effect":1,"effect_value":0.079,"position":7},{"timing_sec":85.358,"notes_attribute":1,"notes_level":1,"effect":1,"effect_value":0.079,"position":6},{"timing_sec":85.437,"notes_attribute":1,"notes_level":1,"effect":1,"effect_value":0.079,"position":4},{"timing_sec":85.516,"notes_attribute":1,"notes_level":1,"effect":1,"effect_value":0.079,"position":6},{"timing_sec":85.674,"notes_attribute":1,"notes_level":1,"effect":1,"effect_value":0.079,"position":5},{"timing_sec":85.831,"notes_attribute":1,"notes_level":1,"effect":1,"effect_value":0.079,"position":4},{"timing_sec":85.989,"notes_attribute":1,"notes_level":1,"effect":1,"effect_value":0.079,"position":7},{"timing_sec":85.989,"notes_attribute":1,"notes_level":1,"effect":1,"effect_value":0.079,"position":3},{"timing_sec":86.305,"notes_attribute":1,"notes_level":1,"effect":1,"effect_value":0.079,"position":7},{"timing_sec":86.305,"notes_attribute":1,"notes_level":1,"effect":1,"effect_value":0.079,"position":3},{"timing_sec":86.463,"notes_attribute":1,"notes_level":1,"effect":1,"effect_value":0.079,"position":5},{"timing_sec":86.621,"notes_attribute":1,"notes_level":1,"effect":1,"effect_value":0.079,"position":4},{"timing_sec":86.621,"notes_attribute":1,"notes_level":1,"effect":1,"effect_value":0.079,"position":6},{"timing_sec":86.937,"notes_attribute":1,"notes_level":1,"effect":1,"effect_value":0.079,"position":7},{"timing_sec":86.937,"notes_attribute":1,"notes_level":1,"effect":1,"effect_value":0.079,"position":3},{"timing_sec":87.252,"notes_attribute":1,"notes_level":1,"effect":1,"effect_value":0.079,"position":4},{"timing_sec":87.41,"notes_attribute":1,"notes_level":1,"effect":1,"effect_value":0.079,"position":5},{"timing_sec":87.568,"notes_attribute":1,"notes_level":1,"effect":2,"effect_value":0.079,"position":6},{"timing_sec":87.726,"notes_attribute":1,"notes_level":1,"effect":1,"effect_value":0.079,"position":3},{"timing_sec":87.726,"notes_attribute":1,"notes_level":1,"effect":1,"effect_value":0.079,"position":7},{"timing_sec":88.042,"notes_attribute":1,"notes_level":1,"effect":3,"effect_value":0.316,"position":4},{"timing_sec":88.042,"notes_attribute":1,"notes_level":1,"effect":3,"effect_value":0.316,"position":6},{"timing_sec":88.516,"notes_attribute":1,"notes_level":1,"effect":1,"effect_value":0.079,"position":3},{"timing_sec":88.516,"notes_attribute":1,"notes_level":1,"effect":1,"effect_value":0.079,"position":7},{"timing_sec":88.831,"notes_attribute":1,"notes_level":1,"effect":1,"effect_value":0.079,"position":5},{"timing_sec":88.989,"notes_attribute":1,"notes_level":1,"effect":1,"effect_value":0.079,"position":5},{"timing_sec":89.147,"notes_attribute":1,"notes_level":1,"effect":1,"effect_value":0.079,"position":5},{"timing_sec":89.305,"notes_attribute":1,"notes_level":1,"effect":4,"effect_value":0.079,"position":7},{"timing_sec":89.305,"notes_attribute":1,"notes_level":1,"effect":4,"effect_value":0.079,"position":4},{"timing_sec":89.463,"notes_attribute":1,"notes_level":1,"effect":1,"effect_value":0.079,"position":3},{"timing_sec":89.463,"notes_attribute":1,"notes_level":1,"effect":1,"effect_value":0.079,"position":6},{"timing_sec":89.779,"notes_attribute":1,"notes_level":1,"effect":1,"effect_value":0.079,"position":6},{"timing_sec":89.779,"notes_attribute":1,"notes_level":1,"effect":1,"effect_value":0.079,"position":4},{"timing_sec":90.095,"notes_attribute":1,"notes_level":1,"effect":1,"effect_value":0.079,"position":7},{"timing_sec":90.095,"notes_attribute":1,"notes_level":1,"effect":1,"effect_value":0.079,"position":3},{"timing_sec":90.41,"notes_attribute":1,"notes_level":1,"effect":3,"effect_value":0.789,"position":6},{"timing_sec":90.41,"notes_attribute":1,"notes_level":1,"effect":1,"effect_value":0.079,"position":4},{"timing_sec":91.2,"notes_attribute":1,"notes_level":1,"effect":1,"effect_value":0.079,"position":4},{"timing_sec":91.516,"notes_attribute":1,"notes_level":1,"effect":1,"effect_value":0.079,"position":4},{"timing_sec":91.516,"notes_attribute":1,"notes_level":1,"effect":1,"effect_value":0.079,"position":6},{"timing_sec":91.831,"notes_attribute":1,"notes_level":1,"effect":4,"effect_value":0.079,"position":3},{"timing_sec":91.831,"notes_attribute":1,"notes_level":1,"effect":1,"effect_value":0.079,"position":6},{"timing_sec":91.989,"notes_attribute":1,"notes_level":1,"effect":1,"effect_value":0.079,"position":7},{"timing_sec":91.989,"notes_attribute":1,"notes_level":1,"effect":2,"effect_value":0.079,"position":4},{"timing_sec":92.305,"notes_attribute":1,"notes_level":1,"effect":1,"effect_value":0.079,"position":4},{"timing_sec":92.305,"notes_attribute":1,"notes_level":1,"effect":1,"effect_value":0.079,"position":6},{"timing_sec":92.463,"notes_attribute":1,"notes_level":1,"effect":1,"effect_value":0.079,"position":3},{"timing_sec":92.621,"notes_attribute":1,"notes_level":1,"effect":1,"effect_value":0.079,"position":4},{"timing_sec":92.779,"notes_attribute":1,"notes_level":1,"effect":1,"effect_value":0.079,"position":7},{"timing_sec":92.937,"notes_attribute":1,"notes_level":1,"effect":1,"effect_value":0.079,"position":6},{"timing_sec":93.095,"notes_attribute":1,"notes_level":1,"effect":4,"effect_value":0.079,"position":4},{"timing_sec":93.095,"notes_attribute":1,"notes_level":1,"effect":1,"effect_value":0.079,"position":7},{"timing_sec":93.252,"notes_attribute":1,"notes_level":1,"effect":4,"effect_value":0.079,"position":6},{"timing_sec":93.252,"notes_attribute":1,"notes_level":1,"effect":1,"effect_value":0.079,"position":3},{"timing_sec":93.41,"notes_attribute":1,"notes_level":1,"effect":4,"effect_value":0.079,"position":4},{"timing_sec":93.41,"notes_attribute":1,"notes_level":1,"effect":1,"effect_value":0.079,"position":7},{"timing_sec":93.568,"notes_attribute":1,"notes_level":1,"effect":4,"effect_value":0.079,"position":6},{"timing_sec":93.568,"notes_attribute":1,"notes_level":1,"effect":1,"effect_value":0.079,"position":3},{"timing_sec":93.884,"notes_attribute":1,"notes_level":1,"effect":1,"effect_value":0.079,"position":4},{"timing_sec":93.884,"notes_attribute":1,"notes_level":1,"effect":1,"effect_value":0.079,"position":6},{"timing_sec":94.042,"notes_attribute":1,"notes_level":1,"effect":4,"effect_value":0.079,"position":7},{"timing_sec":94.042,"notes_attribute":1,"notes_level":1,"effect":4,"effect_value":0.079,"position":3},{"timing_sec":94.358,"notes_attribute":1,"notes_level":1,"effect":1,"effect_value":0.079,"position":5},{"timing_sec":94.516,"notes_attribute":1,"notes_level":1,"effect":1,"effect_value":0.079,"position":5},{"timing_sec":94.674,"notes_attribute":1,"notes_level":1,"effect":1,"effect_value":0.079,"position":4},{"timing_sec":94.674,"notes_attribute":1,"notes_level":1,"effect":1,"effect_value":0.079,"position":6},{"timing_sec":94.989,"notes_attribute":1,"notes_level":1,"effect":3,"effect_value":0.316,"position":7},{"timing_sec":94.989,"notes_attribute":1,"notes_level":1,"effect":1,"effect_value":0.079,"position":3},{"timing_sec":95.305,"notes_attribute":1,"notes_level":1,"effect":1,"effect_value":0.079,"position":3},{"timing_sec":95.463,"notes_attribute":1,"notes_level":1,"effect":1,"effect_value":0.079,"position":5},{"timing_sec":95.621,"notes_attribute":1,"notes_level":1,"effect":2,"effect_value":0.079,"position":4},{"timing_sec":95.779,"notes_attribute":1,"notes_level":1,"effect":1,"effect_value":0.079,"position":6},{"timing_sec":95.937,"notes_attribute":1,"notes_level":1,"effect":1,"effect_value":0.079,"position":5},{"timing_sec":96.095,"notes_attribute":1,"notes_level":1,"effect":1,"effect_value":0.079,"position":7},{"timing_sec":96.252,"notes_attribute":1,"notes_level":1,"effect":3,"effect_value":0.158,"position":6},{"timing_sec":96.568,"notes_attribute":1,"notes_level":1,"effect":4,"effect_value":0.079,"position":5},{"timing_sec":96.568,"notes_attribute":1,"notes_level":1,"effect":1,"effect_value":0.079,"position":7},{"timing_sec":96.726,"notes_attribute":1,"notes_level":1,"effect":1,"effect_value":0.079,"position":6},{"timing_sec":96.805,"notes_attribute":1,"notes_level":1,"effect":1,"effect_value":0.079,"position":4},{"timing_sec":96.884,"notes_attribute":1,"notes_level":1,"effect":1,"effect_value":0.079,"position":6},{"timing_sec":97.042,"notes_attribute":1,"notes_level":1,"effect":1,"effect_value":0.079,"position":5},{"timing_sec":97.2,"notes_attribute":1,"notes_level":1,"effect":1,"effect_value":0.079,"position":6},{"timing_sec":97.2,"notes_attribute":1,"notes_level":1,"effect":1,"effect_value":0.079,"position":4},{"timing_sec":97.516,"notes_attribute":1,"notes_level":1,"effect":3,"effect_value":0.316,"position":3},{"timing_sec":97.516,"notes_attribute":1,"notes_level":1,"effect":1,"effect_value":0.079,"position":7},{"timing_sec":97.831,"notes_attribute":1,"notes_level":1,"effect":1,"effect_value":0.079,"position":7},{"timing_sec":97.989,"notes_attribute":1,"notes_level":1,"effect":1,"effect_value":0.079,"position":5},{"timing_sec":98.147,"notes_attribute":1,"notes_level":1,"effect":1,"effect_value":0.079,"position":6},{"timing_sec":98.305,"notes_attribute":1,"notes_level":1,"effect":1,"effect_value":0.079,"position":4},{"timing_sec":98.463,"notes_attribute":1,"notes_level":1,"effect":1,"effect_value":0.079,"position":5},{"timing_sec":98.621,"notes_attribute":1,"notes_level":1,"effect":1,"effect_value":0.079,"position":3},{"timing_sec":98.779,"notes_attribute":1,"notes_level":1,"effect":3,"effect_value":0.158,"position":4},{"timing_sec":99.095,"notes_attribute":1,"notes_level":1,"effect":4,"effect_value":0.079,"position":5},{"timing_sec":99.095,"notes_attribute":1,"notes_level":1,"effect":1,"effect_value":0.079,"position":3},{"timing_sec":99.252,"notes_attribute":1,"notes_level":1,"effect":1,"effect_value":0.079,"position":4},{"timing_sec":99.331,"notes_attribute":1,"notes_level":1,"effect":1,"effect_value":0.079,"position":6},{"timing_sec":99.41,"notes_attribute":1,"notes_level":1,"effect":1,"effect_value":0.079,"position":4},{"timing_sec":99.568,"notes_attribute":1,"notes_level":1,"effect":2,"effect_value":0.079,"position":5},{"timing_sec":99.726,"notes_attribute":1,"notes_level":1,"effect":1,"effect_value":0.079,"position":6},{"timing_sec":99.726,"notes_attribute":1,"notes_level":1,"effect":1,"effect_value":0.079,"position":4},{"timing_sec":100.042,"notes_attribute":1,"notes_level":1,"effect":3,"effect_value":0.316,"position":7},{"timing_sec":100.042,"notes_attribute":1,"notes_level":1,"effect":1,"effect_value":0.079,"position":3},{"timing_sec":100.358,"notes_attribute":1,"notes_level":1,"effect":1,"effect_value":0.079,"position":3},{"timing_sec":100.516,"notes_attribute":1,"notes_level":1,"effect":1,"effect_value":0.079,"position":5},{"timing_sec":100.674,"notes_attribute":1,"notes_level":1,"effect":1,"effect_value":0.079,"position":4},{"timing_sec":100.831,"notes_attribute":1,"notes_level":1,"effect":1,"effect_value":0.079,"position":6},{"timing_sec":100.989,"notes_attribute":1,"notes_level":1,"effect":1,"effect_value":0.079,"position":5},{"timing_sec":101.147,"notes_attribute":1,"notes_level":1,"effect":1,"effect_value":0.079,"position":7},{"timing_sec":101.305,"notes_attribute":1,"notes_level":1,"effect":1,"effect_value":0.079,"position":6},{"timing_sec":101.305,"notes_attribute":1,"notes_level":1,"effect":1,"effect_value":0.079,"position":4},{"timing_sec":101.621,"notes_attribute":1,"notes_level":1,"effect":4,"effect_value":0.079,"position":7},{"timing_sec":101.621,"notes_attribute":1,"notes_level":1,"effect":1,"effect_value":0.079,"position":3},{"timing_sec":101.937,"notes_attribute":1,"notes_level":1,"effect":1,"effect_value":0.079,"position":7},{"timing_sec":102.095,"notes_attribute":1,"notes_level":1,"effect":1,"effect_value":0.079,"position":6},{"timing_sec":102.252,"notes_attribute":1,"notes_level":1,"effect":1,"effect_value":0.079,"position":5},{"timing_sec":102.41,"notes_attribute":1,"notes_level":1,"effect":1,"effect_value":0.079,"position":4},{"timing_sec":102.568,"notes_attribute":1,"notes_level":1,"effect":1,"effect_value":0.079,"position":3},{"timing_sec":102.726,"notes_attribute":1,"notes_level":1,"effect":1,"effect_value":0.079,"position":7},{"timing_sec":102.884,"notes_attribute":1,"notes_level":1,"effect":1,"effect_value":0.079,"position":6},{"timing_sec":103.042,"notes_attribute":1,"notes_level":1,"effect":1,"effect_value":0.079,"position":5},{"timing_sec":103.2,"notes_attribute":1,"notes_level":1,"effect":3,"effect_value":0.158,"position":3},{"timing_sec":103.516,"notes_attribute":1,"notes_level":1,"effect":3,"effect_value":0.158,"position":7},{"timing_sec":103.831,"notes_attribute":1,"notes_level":1,"effect":3,"effect_value":0.158,"position":5},{"timing_sec":104.147,"notes_attribute":1,"notes_level":1,"effect":4,"effect_value":0.079,"position":7},{"timing_sec":104.147,"notes_attribute":1,"notes_level":1,"effect":4,"effect_value":0.079,"position":3},{"timing_sec":104.463,"notes_attribute":1,"notes_level":1,"effect":2,"effect_value":0.079,"position":6},{"timing_sec":104.621,"notes_attribute":1,"notes_level":1,"effect":1,"effect_value":0.079,"position":5},{"timing_sec":104.779,"notes_attribute":1,"notes_level":1,"effect":1,"effect_value":0.079,"position":7},{"timing_sec":104.779,"notes_attribute":1,"notes_level":1,"effect":1,"effect_value":0.079,"position":4},{"timing_sec":105.095,"notes_attribute":1,"notes_level":1,"effect":3,"effect_value":0.316,"position":3},{"timing_sec":105.095,"notes_attribute":1,"notes_level":1,"effect":1,"effect_value":0.079,"position":6},{"timing_sec":105.41,"notes_attribute":1,"notes_level":1,"effect":1,"effect_value":0.079,"position":7},{"timing_sec":105.568,"notes_attribute":1,"notes_level":1,"effect":1,"effect_value":0.079,"position":5},{"timing_sec":105.726,"notes_attribute":1,"notes_level":1,"effect":1,"effect_value":0.079,"position":6},{"timing_sec":105.884,"notes_attribute":1,"notes_level":1,"effect":1,"effect_value":0.079,"position":4},{"timing_sec":106.042,"notes_attribute":1,"notes_level":1,"effect":1,"effect_value":0.079,"position":5},{"timing_sec":106.2,"notes_attribute":1,"notes_level":1,"effect":1,"effect_value":0.079,"position":3},{"timing_sec":106.358,"notes_attribute":1,"notes_level":1,"effect":3,"effect_value":0.158,"position":4},{"timing_sec":106.674,"notes_attribute":1,"notes_level":1,"effect":4,"effect_value":0.079,"position":7},{"timing_sec":106.674,"notes_attribute":1,"notes_level":1,"effect":1,"effect_value":0.079,"position":3},{"timing_sec":106.831,"notes_attribute":1,"notes_level":1,"effect":1,"effect_value":0.079,"position":6},{"timing_sec":106.91,"notes_attribute":1,"notes_level":1,"effect":1,"effect_value":0.079,"position":4},{"timing_sec":106.989,"notes_attribute":1,"notes_level":1,"effect":1,"effect_value":0.079,"position":6},{"timing_sec":107.147,"notes_attribute":1,"notes_level":1,"effect":1,"effect_value":0.079,"position":5},{"timing_sec":107.305,"notes_attribute":1,"notes_level":1,"effect":1,"effect_value":0.079,"position":3},{"timing_sec":107.463,"notes_attribute":1,"notes_level":1,"effect":1,"effect_value":0.079,"position":7},{"timing_sec":107.621,"notes_attribute":1,"notes_level":1,"effect":1,"effect_value":0.079,"position":5},{"timing_sec":107.779,"notes_attribute":1,"notes_level":1,"effect":2,"effect_value":0.079,"position":6},{"timing_sec":107.937,"notes_attribute":1,"notes_level":1,"effect":1,"effect_value":0.079,"position":4},{"timing_sec":108.095,"notes_attribute":1,"notes_level":1,"effect":1,"effect_value":0.079,"position":7},{"timing_sec":108.252,"notes_attribute":1,"notes_level":1,"effect":1,"effect_value":0.079,"position":3},{"timing_sec":108.41,"notes_attribute":1,"notes_level":1,"effect":1,"effect_value":0.079,"position":4},{"timing_sec":108.568,"notes_attribute":1,"notes_level":1,"effect":1,"effect_value":0.079,"position":3},{"timing_sec":108.726,"notes_attribute":1,"notes_level":1,"effect":1,"effect_value":0.079,"position":5},{"timing_sec":108.884,"notes_attribute":1,"notes_level":1,"effect":3,"effect_value":0.158,"position":4},{"timing_sec":109.2,"notes_attribute":1,"notes_level":1,"effect":4,"effect_value":0.079,"position":7},{"timing_sec":109.2,"notes_attribute":1,"notes_level":1,"effect":1,"effect_value":0.079,"position":3},{"timing_sec":109.358,"notes_attribute":1,"notes_level":1,"effect":1,"effect_value":0.079,"position":4},{"timing_sec":109.437,"notes_attribute":1,"notes_level":1,"effect":1,"effect_value":0.079,"position":6},{"timing_sec":109.516,"notes_attribute":1,"notes_level":1,"effect":1,"effect_value":0.079,"position":4},{"timing_sec":109.674,"notes_attribute":1,"notes_level":1,"effect":1,"effect_value":0.079,"position":5},{"timing_sec":109.831,"notes_attribute":1,"notes_level":1,"effect":1,"effect_value":0.079,"position":3},{"timing_sec":109.831,"notes_attribute":1,"notes_level":1,"effect":1,"effect_value":0.079,"position":6},{"timing_sec":110.147,"notes_attribute":1,"notes_level":1,"effect":3,"effect_value":0.316,"position":7},{"timing_sec":110.147,"notes_attribute":1,"notes_level":1,"effect":1,"effect_value":0.079,"position":4},{"timing_sec":110.463,"notes_attribute":1,"notes_level":1,"effect":1,"effect_value":0.079,"position":3},{"timing_sec":110.621,"notes_attribute":1,"notes_level":1,"effect":1,"effect_value":0.079,"position":5},{"timing_sec":110.779,"notes_attribute":1,"notes_level":1,"effect":1,"effect_value":0.079,"position":4},{"timing_sec":110.937,"notes_attribute":1,"notes_level":1,"effect":1,"effect_value":0.079,"position":6},{"timing_sec":111.095,"notes_attribute":1,"notes_level":1,"effect":1,"effect_value":0.079,"position":5},{"timing_sec":111.252,"notes_attribute":1,"notes_level":1,"effect":1,"effect_value":0.079,"position":7},{"timing_sec":111.41,"notes_attribute":1,"notes_level":1,"effect":1,"effect_value":0.079,"position":6},{"timing_sec":111.41,"notes_attribute":1,"notes_level":1,"effect":1,"effect_value":0.079,"position":4},{"timing_sec":111.726,"notes_attribute":1,"notes_level":1,"effect":4,"effect_value":0.079,"position":7},{"timing_sec":111.726,"notes_attribute":1,"notes_level":1,"effect":1,"effect_value":0.079,"position":3},{"timing_sec":111.884,"notes_attribute":1,"notes_level":1,"effect":3,"effect_value":0.316,"position":3},{"timing_sec":112.2,"notes_attribute":1,"notes_level":1,"effect":1,"effect_value":0.079,"position":5},{"timing_sec":112.358,"notes_attribute":1,"notes_level":1,"effect":2,"effect_value":0.079,"position":6},{"timing_sec":112.516,"notes_attribute":1,"notes_level":1,"effect":1,"effect_value":0.079,"position":7},{"timing_sec":112.674,"notes_attribute":1,"notes_level":1,"effect":1,"effect_value":0.079,"position":3},{"timing_sec":112.674,"notes_attribute":1,"notes_level":1,"effect":1,"effect_value":0.079,"position":7},{"timing_sec":112.989,"notes_attribute":1,"notes_level":1,"effect":1,"effect_value":0.079,"position":6},{"timing_sec":112.989,"notes_attribute":1,"notes_level":1,"effect":1,"effect_value":0.079,"position":4},{"timing_sec":113.147,"notes_attribute":1,"notes_level":1,"effect":3,"effect_value":0.316,"position":7},{"timing_sec":113.463,"notes_attribute":1,"notes_level":1,"effect":1,"effect_value":0.079,"position":3},{"timing_sec":113.621,"notes_attribute":1,"notes_level":1,"effect":1,"effect_value":0.079,"position":4},{"timing_sec":113.779,"notes_attribute":1,"notes_level":1,"effect":3,"effect_value":0.316,"position":3},{"timing_sec":114.095,"notes_attribute":1,"notes_level":1,"effect":1,"effect_value":0.079,"position":7},{"timing_sec":114.252,"notes_attribute":1,"notes_level":1,"effect":1,"effect_value":0.079,"position":6},{"timing_sec":114.41,"notes_attribute":1,"notes_level":1,"effect":3,"effect_value":0.316,"position":7},{"timing_sec":114.726,"notes_attribute":1,"notes_level":1,"effect":1,"effect_value":0.079,"position":5},{"timing_sec":114.884,"notes_attribute":1,"notes_level":1,"effect":1,"effect_value":0.079,"position":4},{"timing_sec":115.042,"notes_attribute":1,"notes_level":1,"effect":1,"effect_value":0.079,"position":3},{"timing_sec":115.2,"notes_attribute":1,"notes_level":1,"effect":1,"effect_value":0.079,"position":7},{"timing_sec":115.2,"notes_attribute":1,"notes_level":1,"effect":1,"effect_value":0.079,"position":3},{"timing_sec":115.516,"notes_attribute":1,"notes_level":1,"effect":1,"effect_value":0.079,"position":4},{"timing_sec":115.516,"notes_attribute":1,"notes_level":1,"effect":1,"effect_value":0.079,"position":6},{"timing_sec":115.831,"notes_attribute":1,"notes_level":1,"effect":1,"effect_value":0.079,"position":4},{"timing_sec":115.831,"notes_attribute":1,"notes_level":1,"effect":1,"effect_value":0.079,"position":6},{"timing_sec":115.989,"notes_attribute":1,"notes_level":1,"effect":1,"effect_value":0.079,"position":5},{"timing_sec":116.147,"notes_attribute":1,"notes_level":1,"effect":1,"effect_value":0.079,"position":5},{"timing_sec":116.305,"notes_attribute":1,"notes_level":1,"effect":4,"effect_value":0.079,"position":7},{"timing_sec":116.305,"notes_attribute":1,"notes_level":1,"effect":2,"effect_value":0.079,"position":3},{"timing_sec":116.621,"notes_attribute":1,"notes_level":1,"effect":1,"effect_value":0.079,"position":3},{"timing_sec":116.621,"notes_attribute":1,"notes_level":1,"effect":1,"effect_value":0.079,"position":6},{"timing_sec":116.779,"notes_attribute":1,"notes_level":1,"effect":1,"effect_value":0.079,"position":5},{"timing_sec":116.937,"notes_attribute":1,"notes_level":1,"effect":4,"effect_value":0.079,"position":7},{"timing_sec":116.937,"notes_attribute":1,"notes_level":1,"effect":1,"effect_value":0.079,"position":4},{"timing_sec":117.252,"notes_attribute":1,"notes_level":1,"effect":1,"effect_value":0.079,"position":4},{"timing_sec":117.252,"notes_attribute":1,"notes_level":1,"effect":1,"effect_value":0.079,"position":7},{"timing_sec":117.41,"notes_attribute":1,"notes_level":1,"effect":1,"effect_value":0.079,"position":5},{"timing_sec":117.568,"notes_attribute":1,"notes_level":1,"effect":4,"effect_value":0.079,"position":3},{"timing_sec":117.568,"notes_attribute":1,"notes_level":1,"effect":1,"effect_value":0.079,"position":6},{"timing_sec":117.884,"notes_attribute":1,"notes_level":1,"effect":4,"effect_value":0.079,"position":6},{"timing_sec":117.884,"notes_attribute":1,"notes_level":1,"effect":1,"effect_value":0.079,"position":4},{"timing_sec":118.042,"notes_attribute":1,"notes_level":1,"effect":4,"effect_value":0.079,"position":6},{"timing_sec":118.042,"notes_attribute":1,"notes_level":1,"effect":1,"effect_value":0.079,"position":4},{"timing_sec":118.2,"notes_attribute":1,"notes_level":1,"effect":4,"effect_value":0.079,"position":7},{"timing_sec":118.2,"notes_attribute":1,"notes_level":1,"effect":1,"effect_value":0.079,"position":3}]