{"live_difficulty_id":33000236,"live_notes":[{"id":1,"call_time":7689,"note_type":2,"note_position":1,"gimmick_id":0,"note_action":1,"wave_id":0,"note_random_drop_color":99,"auto_judge_type":20},{"id":2,"call_time":9109,"note_type":3,"note_position":1,"gimmick_id":0,"note_action":1,"wave_id":0,"note_random_drop_color":99,"auto_judge_type":20},{"id":3,"call_time":9109,"note_type":1,"note_position":2,"gimmick_id":0,"note_action":1,"wave_id":0,"note_random_drop_color":99,"auto_judge_type":20},{"id":4,"call_time":9819,"note_type":1,"note_position":1,"gimmick_id":0,"note_action":1,"wave_id":0,"note_random_drop_color":99,"auto_judge_type":20},{"id":5,"call_time":10529,"note_type":2,"note_position":2,"gimmick_id":0,"note_action":1,"wave_id":0,"note_random_drop_color":99,"auto_judge_type":20},{"id":6,"call_time":11239,"note_type":3,"note_position":2,"gimmick_id":0,"note_action":1,"wave_id":0,"note_random_drop_color":99,"auto_judge_type":20},{"id":7,"call_time":11949,"note_type":1,"note_position":2,"gimmick_id":50000338,"note_action":1,"wave_id":0,"note_random_drop_color":99,"auto_judge_type":20},{"id":8,"call_time":13369,"note_type":2,"note_position":2,"gimmick_id":0,"note_action":1,"wave_id":0,"note_random_drop_color":99,"auto_judge_type":20},{"id":9,"call_time":14789,"note_type":1,"note_position":1,"gimmick_id":0,"note_action":1,"wave_id":0,"note_random_drop_color":99,"auto_judge_type":20},{"id":10,"call_time":14789,"note_type":3,"note_position":2,"gimmick_id":0,"note_action":1,"wave_id":0,"note_random_drop_color":99,"auto_judge_type":20},{"id":11,"call_time":15498,"note_type":4,"note_position":2,"gimmick_id":0,"note_action":1,"wave_id":1,"note_random_drop_color":99,"auto_judge_type":20},{"id":12,"call_time":15499,"note_type":1,"note_position":2,"gimmick_id":0,"note_action":1,"wave_id":1,"note_random_drop_color":99,"auto_judge_type":20},{"id":13,"call_time":16209,"note_type":2,"note_position":1,"gimmick_id":0,"note_action":1,"wave_id":1,"note_random_drop_color":99,"auto_judge_type":20},{"id":14,"call_time":16919,"note_type":3,"note_position":1,"gimmick_id":0,"note_action":1,"wave_id":1,"note_random_drop_color":99,"auto_judge_type":20},{"id":15,"call_time":17452,"note_type":1,"note_position":1,"gimmick_id":0,"note_action":4,"wave_id":1,"note_random_drop_color":99,"auto_judge_type":20},{"id":16,"call_time":19050,"note_type":1,"note_position":1,"gimmick_id":0,"note_action":1,"wave_id":1,"note_random_drop_color":99,"auto_judge_type":20},{"id":17,"call_time":19405,"note_type":1,"note_position":1,"gimmick_id":0,"note_action":1,"wave_id":1,"note_random_drop_color":99,"auto_judge_type":20},{"id":18,"call_time":19760,"note_type":1,"note_position":1,"gimmick_id":0,"note_action":1,"wave_id":1,"note_random_drop_color":99,"auto_judge_type":20},{"id":19,"call_time":19937,"note_type":1,"note_position":2,"gimmick_id":0,"note_action":1,"wave_id":1,"note_random_drop_color":99,"auto_judge_type":20},{"id":20,"call_time":20115,"note_type":1,"note_position":1,"gimmick_id":0,"note_action":1,"wave_id":1,"note_random_drop_color":99,"auto_judge_type":20},{"id":21,"call_time":20116,"note_type":5,"note_position":1,"gimmick_id":0,"note_action":1,"wave_id":1,"note_random_drop_color":99,"auto_judge_type":20},{"id":22,"call_time":20470,"note_type":1,"note_position":1,"gimmick_id":0,"note_action":1,"wave_id":0,"note_random_drop_color":99,"auto_judge_type":20},{"id":23,"call_time":20647,"note_type":1,"note_position":2,"gimmick_id":0,"note_action":1,"wave_id":0,"note_random_drop_color":99,"auto_judge_type":20},{"id":24,"call_time":20825,"note_type":1,"note_position":1,"gimmick_id":0,"note_action":1,"wave_id":0,"note_random_drop_color":99,"auto_judge_type":20},{"id":25,"call_time":21002,"note_type":1,"note_position":2,"gimmick_id":0,"note_action":1,"wave_id":0,"note_random_drop_color":99,"auto_judge_type":20},{"id":26,"call_time":21357,"note_type":1,"note_position":2,"gimmick_id":0,"note_action":1,"wave_id":0,"note_random_drop_color":99,"auto_judge_type":20},{"id":27,"call_time":21535,"note_type":1,"note_position":2,"gimmick_id":0,"note_action":1,"wave_id":0,"note_random_drop_color":99,"auto_judge_type":20},{"id":28,"call_time":21890,"note_type":1,"note_position":2,"gimmick_id":50000337,"note_action":1,"wave_id":0,"note_random_drop_color":99,"auto_judge_type":20},{"id":29,"call_time":22245,"note_type":1,"note_position":2,"gimmick_id":0,"note_action":1,"wave_id":0,"note_random_drop_color":99,"auto_judge_type":20},{"id":30,"call_time":22600,"note_type":1,"note_position":2,"gimmick_id":0,"note_action":1,"wave_id":0,"note_random_drop_color":99,"auto_judge_type":20},{"id":31,"call_time":22776,"note_type":4,"note_position":1,"gimmick_id":0,"note_action":1,"wave_id":2,"note_random_drop_color":99,"auto_judge_type":20},{"id":32,"call_time":22777,"note_type":1,"note_position":1,"gimmick_id":0,"note_action":1,"wave_id":2,"note_random_drop_color":99,"auto_judge_type":20},{"id":33,"call_time":22955,"note_type":1,"note_position":2,"gimmick_id":0,"note_action":1,"wave_id":2,"note_random_drop_color":99,"auto_judge_type":20},{"id":34,"call_time":23310,"note_type":1,"note_position":2,"gimmick_id":0,"note_action":1,"wave_id":2,"note_random_drop_color":99,"auto_judge_type":20},{"id":35,"call_time":23487,"note_type":1,"note_position":1,"gimmick_id":0,"note_action":1,"wave_id":2,"note_random_drop_color":99,"auto_judge_type":20},{"id":36,"call_time":23665,"note_type":1,"note_position":2,"gimmick_id":0,"note_action":1,"wave_id":2,"note_random_drop_color":99,"auto_judge_type":20},{"id":37,"call_time":23842,"note_type":1,"note_position":1,"gimmick_id":0,"note_action":1,"wave_id":2,"note_random_drop_color":99,"auto_judge_type":20},{"id":38,"call_time":24198,"note_type":1,"note_position":1,"gimmick_id":0,"note_action":1,"wave_id":2,"note_random_drop_color":99,"auto_judge_type":20},{"id":39,"call_time":24375,"note_type":1,"note_position":1,"gimmick_id":0,"note_action":1,"wave_id":2,"note_random_drop_color":99,"auto_judge_type":20},{"id":40,"call_time":24376,"note_type":5,"note_position":1,"gimmick_id":0,"note_action":1,"wave_id":2,"note_random_drop_color":99,"auto_judge_type":20},{"id":41,"call_time":24730,"note_type":1,"note_position":2,"gimmick_id":0,"note_action":1,"wave_id":0,"note_random_drop_color":99,"auto_judge_type":20},{"id":42,"call_time":26150,"note_type":1,"note_position":1,"gimmick_id":0,"note_action":1,"wave_id":0,"note_random_drop_color":99,"auto_judge_type":20},{"id":43,"call_time":26860,"note_type":1,"note_position":2,"gimmick_id":0,"note_action":1,"wave_id":0,"note_random_drop_color":99,"auto_judge_type":20},{"id":44,"call_time":27570,"note_type":1,"note_position":1,"gimmick_id":0,"note_action":4,"wave_id":0,"note_random_drop_color":99,"auto_judge_type":20},{"id":45,"call_time":28280,"note_type":1,"note_position":1,"gimmick_id":0,"note_action":7,"wave_id":0,"note_random_drop_color":99,"auto_judge_type":20},{"id":46,"call_time":28990,"note_type":1,"note_position":2,"gimmick_id":0,"note_action":1,"wave_id":0,"note_random_drop_color":99,"auto_judge_type":20},{"id":47,"call_time":29700,"note_type":1,"note_position":2,"gimmick_id":0,"note_action":1,"wave_id":0,"note_random_drop_color":99,"auto_judge_type":20},{"id":48,"call_time":30411,"note_type":1,"note_position":2,"gimmick_id":0,"note_action":1,"wave_id":0,"note_random_drop_color":99,"auto_judge_type":20},{"id":49,"call_time":31831,"note_type":1,"note_position":1,"gimmick_id":0,"note_action":1,"wave_id":0,"note_random_drop_color":99,"auto_judge_type":20},{"id":50,"call_time":32541,"note_type":1,"note_position":1,"gimmick_id":0,"note_action":1,"wave_id":0,"note_random_drop_color":99,"auto_judge_type":20},{"id":51,"call_time":33251,"note_type":1,"note_position":2,"gimmick_id":0,"note_action":5,"wave_id":0,"note_random_drop_color":99,"auto_judge_type":20},{"id":52,"call_time":33961,"note_type":1,"note_position":1,"gimmick_id":0,"note_action":4,"wave_id":0,"note_random_drop_color":99,"auto_judge_type":20},{"id":53,"call_time":34671,"note_type":1,"note_position":2,"gimmick_id":0,"note_action":4,"wave_id":0,"note_random_drop_color":99,"auto_judge_type":20},{"id":54,"call_time":35381,"note_type":1,"note_position":1,"gimmick_id":0,"note_action":1,"wave_id":0,"note_random_drop_color":99,"auto_judge_type":20},{"id":55,"call_time":35381,"note_type":1,"note_position":2,"gimmick_id":0,"note_action":1,"wave_id":0,"note_random_drop_color":99,"auto_judge_type":20},{"id":56,"call_time":36091,"note_type":2,"note_position":1,"gimmick_id":0,"note_action":1,"wave_id":0,"note_random_drop_color":99,"auto_judge_type":20},{"id":57,"call_time":36801,"note_type":1,"note_position":2,"gimmick_id":0,"note_action":1,"wave_id":0,"note_random_drop_color":99,"auto_judge_type":20},{"id":58,"call_time":37511,"note_type":3,"note_position":1,"gimmick_id":0,"note_action":1,"wave_id":0,"note_random_drop_color":99,"auto_judge_type":20},{"id":59,"call_time":37511,"note_type":1,"note_position":2,"gimmick_id":0,"note_action":1,"wave_id":0,"note_random_drop_color":99,"auto_judge_type":20},{"id":60,"call_time":38221,"note_type":1,"note_position":1,"gimmick_id":0,"note_action":1,"wave_id":0,"note_random_drop_color":99,"auto_judge_type":20},{"id":61,"call_time":38931,"note_type":2,"note_position":2,"gimmick_id":0,"note_action":1,"wave_id":0,"note_random_drop_color":99,"auto_judge_type":20},{"id":62,"call_time":39641,"note_type":1,"note_position":1,"gimmick_id":0,"note_action":1,"wave_id":0,"note_random_drop_color":99,"auto_judge_type":20},{"id":63,"call_time":40351,"note_type":1,"note_position":1,"gimmick_id":0,"note_action":1,"wave_id":0,"note_random_drop_color":99,"auto_judge_type":20},{"id":64,"call_time":40351,"note_type":3,"note_position":2,"gimmick_id":0,"note_action":1,"wave_id":0,"note_random_drop_color":99,"auto_judge_type":20},{"id":65,"call_time":41061,"note_type":1,"note_position":2,"gimmick_id":50000339,"note_action":1,"wave_id":0,"note_random_drop_color":99,"auto_judge_type":20},{"id":66,"call_time":41770,"note_type":4,"note_position":2,"gimmick_id":0,"note_action":1,"wave_id":3,"note_random_drop_color":99,"auto_judge_type":20},{"id":67,"call_time":41771,"note_type":1,"note_position":2,"gimmick_id":0,"note_action":1,"wave_id":3,"note_random_drop_color":99,"auto_judge_type":20},{"id":68,"call_time":42482,"note_type":1,"note_position":1,"gimmick_id":0,"note_action":1,"wave_id":3,"note_random_drop_color":99,"auto_judge_type":20},{"id":69,"call_time":43192,"note_type":1,"note_position":2,"gimmick_id":0,"note_action":1,"wave_id":3,"note_random_drop_color":99,"auto_judge_type":20},{"id":70,"call_time":43902,"note_type":1,"note_position":1,"gimmick_id":0,"note_action":1,"wave_id":3,"note_random_drop_color":99,"auto_judge_type":20},{"id":71,"call_time":44612,"note_type":1,"note_position":2,"gimmick_id":0,"note_action":1,"wave_id":3,"note_random_drop_color":99,"auto_judge_type":20},{"id":72,"call_time":44967,"note_type":1,"note_position":1,"gimmick_id":0,"note_action":1,"wave_id":3,"note_random_drop_color":99,"auto_judge_type":20},{"id":73,"call_time":45322,"note_type":1,"note_position":2,"gimmick_id":0,"note_action":1,"wave_id":3,"note_random_drop_color":99,"auto_judge_type":20},{"id":74,"call_time":45677,"note_type":1,"note_position":1,"gimmick_id":0,"note_action":1,"wave_id":3,"note_random_drop_color":99,"auto_judge_type":20},{"id":75,"call_time":46032,"note_type":1,"note_position":2,"gimmick_id":0,"note_action":1,"wave_id":3,"note_random_drop_color":99,"auto_judge_type":20},{"id":76,"call_time":46387,"note_type":1,"note_position":1,"gimmick_id":0,"note_action":1,"wave_id":3,"note_random_drop_color":99,"auto_judge_type":20},{"id":77,"call_time":46564,"note_type":2,"note_position":2,"gimmick_id":0,"note_action":1,"wave_id":3,"note_random_drop_color":99,"auto_judge_type":20},{"id":78,"call_time":47097,"note_type":3,"note_position":2,"gimmick_id":0,"note_action":1,"wave_id":3,"note_random_drop_color":99,"auto_judge_type":20},{"id":79,"call_time":47452,"note_type":1,"note_position":1,"gimmick_id":0,"note_action":7,"wave_id":3,"note_random_drop_color":99,"auto_judge_type":20},{"id":80,"call_time":48162,"note_type":1,"note_position":1,"gimmick_id":0,"note_action":1,"wave_id":3,"note_random_drop_color":99,"auto_judge_type":20},{"id":81,"call_time":48872,"note_type":1,"note_position":2,"gimmick_id":0,"note_action":6,"wave_id":3,"note_random_drop_color":99,"auto_judge_type":20},{"id":82,"call_time":49582,"note_type":1,"note_position":2,"gimmick_id":0,"note_action":1,"wave_id":3,"note_random_drop_color":99,"auto_judge_type":20},{"id":83,"call_time":49583,"note_type":5,"note_position":2,"gimmick_id":0,"note_action":1,"wave_id":3,"note_random_drop_color":99,"auto_judge_type":20},{"id":84,"call_time":50292,"note_type":1,"note_position":1,"gimmick_id":0,"note_action":4,"wave_id":0,"note_random_drop_color":99,"auto_judge_type":20},{"id":85,"call_time":50292,"note_type":1,"note_position":2,"gimmick_id":0,"note_action":4,"wave_id":0,"note_random_drop_color":99,"auto_judge_type":20},{"id":86,"call_time":51002,"note_type":1,"note_position":1,"gimmick_id":50000338,"note_action":1,"wave_id":0,"note_random_drop_color":99,"auto_judge_type":20},{"id":87,"call_time":51712,"note_type":1,"note_position":1,"gimmick_id":0,"note_action":1,"wave_id":0,"note_random_drop_color":99,"auto_judge_type":20},{"id":88,"call_time":51712,"note_type":1,"note_position":2,"gimmick_id":0,"note_action":1,"wave_id":0,"note_random_drop_color":99,"auto_judge_type":20},{"id":89,"call_time":52955,"note_type":1,"note_position":1,"gimmick_id":0,"note_action":1,"wave_id":0,"note_random_drop_color":99,"auto_judge_type":20},{"id":90,"call_time":52955,"note_type":1,"note_position":2,"gimmick_id":0,"note_action":1,"wave_id":0,"note_random_drop_color":99,"auto_judge_type":20},{"id":91,"call_time":53842,"note_type":4,"note_position":2,"gimmick_id":0,"note_action":1,"wave_id":4,"note_random_drop_color":99,"auto_judge_type":20},{"id":92,"call_time":53843,"note_type":1,"note_position":2,"gimmick_id":0,"note_action":1,"wave_id":4,"note_random_drop_color":99,"auto_judge_type":20},{"id":93,"call_time":54375,"note_type":1,"note_position":1,"gimmick_id":0,"note_action":4,"wave_id":4,"note_random_drop_color":99,"auto_judge_type":20},{"id":94,"call_time":55085,"note_type":1,"note_position":1,"gimmick_id":0,"note_action":4,"wave_id":4,"note_random_drop_color":99,"auto_judge_type":20},{"id":95,"call_time":55973,"note_type":1,"note_position":2,"gimmick_id":0,"note_action":1,"wave_id":4,"note_random_drop_color":99,"auto_judge_type":20},{"id":96,"call_time":56683,"note_type":1,"note_position":1,"gimmick_id":0,"note_action":1,"wave_id":4,"note_random_drop_color":99,"auto_judge_type":20},{"id":97,"call_time":57393,"note_type":1,"note_position":2,"gimmick_id":0,"note_action":1,"wave_id":4,"note_random_drop_color":99,"auto_judge_type":20},{"id":98,"call_time":58103,"note_type":1,"note_position":1,"gimmick_id":0,"note_action":1,"wave_id":4,"note_random_drop_color":99,"auto_judge_type":20},{"id":99,"call_time":58813,"note_type":1,"note_position":2,"gimmick_id":0,"note_action":1,"wave_id":4,"note_random_drop_color":99,"auto_judge_type":20},{"id":100,"call_time":59168,"note_type":1,"note_position":1,"gimmick_id":0,"note_action":1,"wave_id":4,"note_random_drop_color":99,"auto_judge_type":20},{"id":101,"call_time":59523,"note_type":1,"note_position":2,"gimmick_id":0,"note_action":1,"wave_id":4,"note_random_drop_color":99,"auto_judge_type":20},{"id":102,"call_time":59701,"note_type":1,"note_position":1,"gimmick_id":0,"note_action":1,"wave_id":4,"note_random_drop_color":99,"auto_judge_type":20},{"id":103,"call_time":59878,"note_type":1,"note_position":2,"gimmick_id":0,"note_action":1,"wave_id":4,"note_random_drop_color":99,"auto_judge_type":20},{"id":104,"call_time":60056,"note_type":1,"note_position":1,"gimmick_id":0,"note_action":1,"wave_id":4,"note_random_drop_color":99,"auto_judge_type":20},{"id":105,"call_time":60057,"note_type":5,"note_position":1,"gimmick_id":0,"note_action":1,"wave_id":4,"note_random_drop_color":99,"auto_judge_type":20},{"id":106,"call_time":60411,"note_type":1,"note_position":1,"gimmick_id":0,"note_action":1,"wave_id":0,"note_random_drop_color":99,"auto_judge_type":20},{"id":107,"call_time":60588,"note_type":1,"note_position":1,"gimmick_id":0,"note_action":4,"wave_id":0,"note_random_drop_color":99,"auto_judge_type":20},{"id":108,"call_time":61653,"note_type":1,"note_position":1,"gimmick_id":0,"note_action":4,"wave_id":0,"note_random_drop_color":99,"auto_judge_type":20},{"id":109,"call_time":61653,"note_type":1,"note_position":2,"gimmick_id":0,"note_action":4,"wave_id":0,"note_random_drop_color":99,"auto_judge_type":20},{"id":110,"call_time":62363,"note_type":1,"note_position":1,"gimmick_id":50000337,"note_action":1,"wave_id":0,"note_random_drop_color":99,"auto_judge_type":20},{"id":111,"call_time":63073,"note_type":1,"note_position":1,"gimmick_id":0,"note_action":7,"wave_id":0,"note_random_drop_color":99,"auto_judge_type":20},{"id":112,"call_time":63073,"note_type":1,"note_position":2,"gimmick_id":0,"note_action":7,"wave_id":0,"note_random_drop_color":99,"auto_judge_type":20},{"id":113,"call_time":63783,"note_type":1,"note_position":2,"gimmick_id":0,"note_action":1,"wave_id":0,"note_random_drop_color":99,"auto_judge_type":20},{"id":114,"call_time":64492,"note_type":4,"note_position":1,"gimmick_id":0,"note_action":1,"wave_id":5,"note_random_drop_color":99,"auto_judge_type":20},{"id":115,"call_time":64493,"note_type":1,"note_position":1,"gimmick_id":0,"note_action":1,"wave_id":5,"note_random_drop_color":99,"auto_judge_type":20},{"id":116,"call_time":65203,"note_type":1,"note_position":1,"gimmick_id":0,"note_action":1,"wave_id":5,"note_random_drop_color":99,"auto_judge_type":20},{"id":117,"call_time":65914,"note_type":1,"note_position":2,"gimmick_id":0,"note_action":7,"wave_id":5,"note_random_drop_color":99,"auto_judge_type":20},{"id":118,"call_time":66446,"note_type":1,"note_position":2,"gimmick_id":0,"note_action":4,"wave_id":5,"note_random_drop_color":99,"auto_judge_type":20},{"id":119,"call_time":67334,"note_type":1,"note_position":1,"gimmick_id":0,"note_action":4,"wave_id":5,"note_random_drop_color":99,"auto_judge_type":20},{"id":120,"call_time":67334,"note_type":1,"note_position":2,"gimmick_id":0,"note_action":4,"wave_id":5,"note_random_drop_color":99,"auto_judge_type":20},{"id":121,"call_time":68044,"note_type":1,"note_position":1,"gimmick_id":0,"note_action":1,"wave_id":5,"note_random_drop_color":99,"auto_judge_type":20},{"id":122,"call_time":68045,"note_type":5,"note_position":1,"gimmick_id":0,"note_action":1,"wave_id":5,"note_random_drop_color":99,"auto_judge_type":20},{"id":123,"call_time":68754,"note_type":1,"note_position":1,"gimmick_id":0,"note_action":4,"wave_id":0,"note_random_drop_color":99,"auto_judge_type":20},{"id":124,"call_time":68754,"note_type":1,"note_position":2,"gimmick_id":0,"note_action":4,"wave_id":0,"note_random_drop_color":99,"auto_judge_type":20},{"id":125,"call_time":70174,"note_type":1,"note_position":2,"gimmick_id":0,"note_action":1,"wave_id":0,"note_random_drop_color":99,"auto_judge_type":20},{"id":126,"call_time":70884,"note_type":1,"note_position":1,"gimmick_id":50000339,"note_action":1,"wave_id":0,"note_random_drop_color":99,"auto_judge_type":20},{"id":127,"call_time":71594,"note_type":1,"note_position":2,"gimmick_id":0,"note_action":6,"wave_id":0,"note_random_drop_color":99,"auto_judge_type":20},{"id":128,"call_time":71948,"note_type":4,"note_position":1,"gimmick_id":0,"note_action":1,"wave_id":6,"note_random_drop_color":99,"auto_judge_type":20},{"id":129,"call_time":71949,"note_type":1,"note_position":1,"gimmick_id":0,"note_action":1,"wave_id":6,"note_random_drop_color":99,"auto_judge_type":20},{"id":130,"call_time":72304,"note_type":1,"note_position":1,"gimmick_id":0,"note_action":1,"wave_id":6,"note_random_drop_color":99,"auto_judge_type":20},{"id":131,"call_time":72659,"note_type":1,"note_position":2,"gimmick_id":0,"note_action":1,"wave_id":6,"note_random_drop_color":99,"auto_judge_type":20},{"id":132,"call_time":73014,"note_type":1,"note_position":1,"gimmick_id":0,"note_action":4,"wave_id":6,"note_random_drop_color":99,"auto_judge_type":20},{"id":133,"call_time":73014,"note_type":1,"note_position":2,"gimmick_id":0,"note_action":4,"wave_id":6,"note_random_drop_color":99,"auto_judge_type":20},{"id":134,"call_time":73724,"note_type":1,"note_position":1,"gimmick_id":0,"note_action":1,"wave_id":6,"note_random_drop_color":99,"auto_judge_type":20},{"id":135,"call_time":74434,"note_type":1,"note_position":1,"gimmick_id":0,"note_action":7,"wave_id":6,"note_random_drop_color":99,"auto_judge_type":20},{"id":136,"call_time":74434,"note_type":1,"note_position":2,"gimmick_id":0,"note_action":7,"wave_id":6,"note_random_drop_color":99,"auto_judge_type":20},{"id":137,"call_time":75144,"note_type":1,"note_position":2,"gimmick_id":0,"note_action":1,"wave_id":6,"note_random_drop_color":99,"auto_judge_type":20},{"id":138,"call_time":75854,"note_type":1,"note_position":1,"gimmick_id":0,"note_action":1,"wave_id":6,"note_random_drop_color":99,"auto_judge_type":20},{"id":139,"call_time":76387,"note_type":1,"note_position":2,"gimmick_id":0,"note_action":1,"wave_id":6,"note_random_drop_color":99,"auto_judge_type":20},{"id":140,"call_time":76742,"note_type":1,"note_position":2,"gimmick_id":0,"note_action":1,"wave_id":6,"note_random_drop_color":99,"auto_judge_type":20},{"id":141,"call_time":77097,"note_type":1,"note_position":1,"gimmick_id":0,"note_action":1,"wave_id":6,"note_random_drop_color":99,"auto_judge_type":20},{"id":142,"call_time":77097,"note_type":1,"note_position":2,"gimmick_id":0,"note_action":1,"wave_id":6,"note_random_drop_color":99,"auto_judge_type":20},{"id":143,"call_time":78695,"note_type":1,"note_position":1,"gimmick_id":0,"note_action":1,"wave_id":6,"note_random_drop_color":99,"auto_judge_type":20},{"id":144,"call_time":79405,"note_type":1,"note_position":2,"gimmick_id":0,"note_action":1,"wave_id":6,"note_random_drop_color":99,"auto_judge_type":20},{"id":145,"call_time":80115,"note_type":1,"note_position":1,"gimmick_id":0,"note_action":1,"wave_id":6,"note_random_drop_color":99,"auto_judge_type":20},{"id":146,"call_time":80825,"note_type":1,"note_position":2,"gimmick_id":0,"note_action":1,"wave_id":6,"note_random_drop_color":99,"auto_judge_type":20},{"id":147,"call_time":80826,"note_type":5,"note_position":2,"gimmick_id":0,"note_action":1,"wave_id":6,"note_random_drop_color":99,"auto_judge_type":20},{"id":148,"call_time":81535,"note_type":1,"note_position":1,"gimmick_id":0,"note_action":4,"wave_id":0,"note_random_drop_color":99,"auto_judge_type":20},{"id":149,"call_time":81535,"note_type":1,"note_position":2,"gimmick_id":0,"note_action":4,"wave_id":0,"note_random_drop_color":99,"auto_judge_type":20},{"id":150,"call_time":82955,"note_type":1,"note_position":1,"gimmick_id":0,"note_action":1,"wave_id":0,"note_random_drop_color":99,"auto_judge_type":20},{"id":151,"call_time":82955,"note_type":1,"note_position":2,"gimmick_id":0,"note_action":1,"wave_id":0,"note_random_drop_color":99,"auto_judge_type":20},{"id":152,"call_time":84375,"note_type":1,"note_position":1,"gimmick_id":0,"note_action":4,"wave_id":0,"note_random_drop_color":99,"auto_judge_type":20},{"id":153,"call_time":85618,"note_type":1,"note_position":1,"gimmick_id":0,"note_action":1,"wave_id":0,"note_random_drop_color":99,"auto_judge_type":20},{"id":154,"call_time":85973,"note_type":1,"note_position":1,"gimmick_id":0,"note_action":1,"wave_id":0,"note_random_drop_color":99,"auto_judge_type":20},{"id":155,"call_time":86150,"note_type":1,"note_position":2,"gimmick_id":0,"note_action":1,"wave_id":0,"note_random_drop_color":99,"auto_judge_type":20},{"id":156,"call_time":86328,"note_type":1,"note_position":1,"gimmick_id":0,"note_action":1,"wave_id":0,"note_random_drop_color":99,"auto_judge_type":20},{"id":157,"call_time":86505,"note_type":1,"note_position":2,"gimmick_id":50000338,"note_action":1,"wave_id":0,"note_random_drop_color":99,"auto_judge_type":20},{"id":158,"call_time":86860,"note_type":1,"note_position":1,"gimmick_id":0,"note_action":1,"wave_id":0,"note_random_drop_color":99,"auto_judge_type":20},{"id":159,"call_time":86860,"note_type":1,"note_position":2,"gimmick_id":0,"note_action":1,"wave_id":0,"note_random_drop_color":99,"auto_judge_type":20},{"id":160,"call_time":87214,"note_type":4,"note_position":1,"gimmick_id":0,"note_action":1,"wave_id":7,"note_random_drop_color":99,"auto_judge_type":20},{"id":161,"call_time":87215,"note_type":1,"note_position":1,"gimmick_id":0,"note_action":1,"wave_id":7,"note_random_drop_color":99,"auto_judge_type":20},{"id":162,"call_time":87925,"note_type":1,"note_position":1,"gimmick_id":0,"note_action":1,"wave_id":7,"note_random_drop_color":99,"auto_judge_type":20},{"id":163,"call_time":88635,"note_type":1,"note_position":2,"gimmick_id":0,"note_action":1,"wave_id":7,"note_random_drop_color":99,"auto_judge_type":20},{"id":164,"call_time":89346,"note_type":1,"note_position":2,"gimmick_id":0,"note_action":1,"wave_id":7,"note_random_drop_color":99,"auto_judge_type":20},{"id":165,"call_time":90056,"note_type":1,"note_position":1,"gimmick_id":0,"note_action":1,"wave_id":7,"note_random_drop_color":99,"auto_judge_type":20},{"id":166,"call_time":90766,"note_type":1,"note_position":2,"gimmick_id":0,"note_action":1,"wave_id":7,"note_random_drop_color":99,"auto_judge_type":20},{"id":167,"call_time":91476,"note_type":1,"note_position":1,"gimmick_id":0,"note_action":1,"wave_id":7,"note_random_drop_color":99,"auto_judge_type":20},{"id":168,"call_time":91831,"note_type":1,"note_position":2,"gimmick_id":0,"note_action":1,"wave_id":7,"note_random_drop_color":99,"auto_judge_type":20},{"id":169,"call_time":92186,"note_type":1,"note_position":1,"gimmick_id":0,"note_action":1,"wave_id":7,"note_random_drop_color":99,"auto_judge_type":20},{"id":170,"call_time":92541,"note_type":1,"note_position":2,"gimmick_id":0,"note_action":1,"wave_id":7,"note_random_drop_color":99,"auto_judge_type":20},{"id":171,"call_time":92896,"note_type":1,"note_position":1,"gimmick_id":0,"note_action":1,"wave_id":7,"note_random_drop_color":99,"auto_judge_type":20},{"id":172,"call_time":93606,"note_type":1,"note_position":2,"gimmick_id":0,"note_action":1,"wave_id":7,"note_random_drop_color":99,"auto_judge_type":20},{"id":173,"call_time":94316,"note_type":1,"note_position":1,"gimmick_id":0,"note_action":1,"wave_id":7,"note_random_drop_color":99,"auto_judge_type":20},{"id":174,"call_time":95026,"note_type":1,"note_position":1,"gimmick_id":0,"note_action":1,"wave_id":7,"note_random_drop_color":99,"auto_judge_type":20},{"id":175,"call_time":95027,"note_type":5,"note_position":1,"gimmick_id":0,"note_action":1,"wave_id":7,"note_random_drop_color":99,"auto_judge_type":20},{"id":176,"call_time":95736,"note_type":1,"note_position":1,"gimmick_id":0,"note_action":4,"wave_id":0,"note_random_drop_color":99,"auto_judge_type":20},{"id":177,"call_time":95736,"note_type":1,"note_position":2,"gimmick_id":0,"note_action":4,"wave_id":0,"note_random_drop_color":99,"auto_judge_type":20},{"id":178,"call_time":96979,"note_type":1,"note_position":2,"gimmick_id":0,"note_action":4,"wave_id":0,"note_random_drop_color":99,"auto_judge_type":20},{"id":179,"call_time":97866,"note_type":1,"note_position":2,"gimmick_id":0,"note_action":1,"wave_id":0,"note_random_drop_color":99,"auto_judge_type":20},{"id":180,"call_time":98221,"note_type":1,"note_position":1,"gimmick_id":0,"note_action":1,"wave_id":0,"note_random_drop_color":99,"auto_judge_type":20},{"id":181,"call_time":98576,"note_type":1,"note_position":1,"gimmick_id":0,"note_action":1,"wave_id":0,"note_random_drop_color":99,"auto_judge_type":20},{"id":182,"call_time":98576,"note_type":1,"note_position":2,"gimmick_id":0,"note_action":1,"wave_id":0,"note_random_drop_color":99,"auto_judge_type":20},{"id":183,"call_time":99819,"note_type":1,"note_position":1,"gimmick_id":0,"note_action":1,"wave_id":0,"note_random_drop_color":99,"auto_judge_type":20},{"id":184,"call_time":100174,"note_type":1,"note_position":1,"gimmick_id":0,"note_action":1,"wave_id":0,"note_random_drop_color":99,"auto_judge_type":20},{"id":185,"call_time":100351,"note_type":1,"note_position":2,"gimmick_id":0,"note_action":1,"wave_id":0,"note_random_drop_color":99,"auto_judge_type":20},{"id":186,"call_time":100529,"note_type":1,"note_position":1,"gimmick_id":0,"note_action":1,"wave_id":0,"note_random_drop_color":99,"auto_judge_type":20},{"id":187,"call_time":100706,"note_type":1,"note_position":2,"gimmick_id":0,"note_action":1,"wave_id":0,"note_random_drop_color":99,"auto_judge_type":20},{"id":188,"call_time":101062,"note_type":1,"note_position":1,"gimmick_id":0,"note_action":1,"wave_id":0,"note_random_drop_color":99,"auto_judge_type":20},{"id":189,"call_time":101062,"note_type":1,"note_position":2,"gimmick_id":0,"note_action":1,"wave_id":0,"note_random_drop_color":99,"auto_judge_type":20}],"live_wave_settings":[{"id":1,"wave_damage":12000,"mission_type":1,"arg_1":96000,"arg_2":0,"reward_voltage":237000},{"id":2,"wave_damage":12000,"mission_type":6,"arg_1":57000,"arg_2":0,"reward_voltage":237000},{"id":3,"wave_damage":12000,"mission_type":1,"arg_1":253000,"arg_2":0,"reward_voltage":237000},{"id":4,"wave_damage":12000,"mission_type":1,"arg_1":139000,"arg_2":0,"reward_voltage":237000},{"id":5,"wave_damage":25000,"mission_type":6,"arg_1":57000,"arg_2":0,"reward_voltage":475000},{"id":6,"wave_damage":12000,"mission_type":1,"arg_1":193000,"arg_2":0,"reward_voltage":237000},{"id":7,"wave_damage":25000,"mission_type":1,"arg_1":229000,"arg_2":0,"reward_voltage":475000}],"note_gimmicks":[{"uniq_id":2001,"id":50000337,"note_gimmick_type":1,"arg_1":0,"arg_2":0,"effect_m_id":50057701,"icon_type":11},{"uniq_id":2002,"id":50000338,"note_gimmick_type":1,"arg_1":0,"arg_2":0,"effect_m_id":50057801,"icon_type":7},{"uniq_id":2003,"id":50000339,"note_gimmick_type":1,"arg_1":0,"arg_2":0,"effect_m_id":50057901,"icon_type":2}],"stage_gimmick_dict":[2,[{"gimmick_master_id":3000364,"condition_master_id_1":1,"condition_master_id_2":1,"skill_master_id":50005901,"uniq_id":1001}]]}